{
"meta":{"test_sets":[],"test_metrics":[],"learn_metrics":[{"best_value":"Min","name":"RMSE"}],"launch_mode":"Train","parameters":"","iteration_count":1000,"learn_sets":["learn"],"name":"experiment"},
"iterations":[
{"learn":[14.59871775],"iteration":0,"passed_time":0.1704660991,"remaining_time":170.295633},
{"learn":[14.22518863],"iteration":1,"passed_time":0.1719656476,"remaining_time":85.81085814},
{"learn":[13.8866124],"iteration":2,"passed_time":0.1732230698,"remaining_time":57.5678002},
{"learn":[13.52356875],"iteration":3,"passed_time":0.1742528015,"remaining_time":43.38894756},
{"learn":[13.18870211],"iteration":4,"passed_time":0.1751590462,"remaining_time":34.85665019},
{"learn":[12.9124226],"iteration":5,"passed_time":0.1760853869,"remaining_time":29.1714791},
{"learn":[12.60003351],"iteration":6,"passed_time":0.1769823988,"remaining_time":25.10621742},
{"learn":[12.32990573],"iteration":7,"passed_time":0.1778687336,"remaining_time":22.05572296},
{"learn":[12.0660619],"iteration":8,"passed_time":0.1785097827,"remaining_time":19.65591052},
{"learn":[11.77309809],"iteration":9,"passed_time":0.1791533592,"remaining_time":17.73618256},
{"learn":[11.49227636],"iteration":10,"passed_time":0.1798169785,"remaining_time":16.16718106},
{"learn":[11.26264833],"iteration":11,"passed_time":0.1804776319,"remaining_time":14.85932502},
{"learn":[11.04260393],"iteration":12,"passed_time":0.1811208176,"remaining_time":13.75124977},
{"learn":[10.79916926],"iteration":13,"passed_time":0.1819592975,"remaining_time":12.81513338},
{"learn":[10.5541002],"iteration":14,"passed_time":0.1834571333,"remaining_time":12.04701842},
{"learn":[10.31918115],"iteration":15,"passed_time":0.1841916246,"remaining_time":11.32778491},
{"learn":[10.10004441],"iteration":16,"passed_time":0.184958172,"remaining_time":10.6949343},
{"learn":[9.894556723],"iteration":17,"passed_time":0.1856232338,"remaining_time":10.12677864},
{"learn":[9.690174082],"iteration":18,"passed_time":0.1862793423,"remaining_time":9.617896569},
{"learn":[9.506034866],"iteration":19,"passed_time":0.186922191,"remaining_time":9.159187357},
{"learn":[9.338524633],"iteration":20,"passed_time":0.1876419992,"remaining_time":8.747691297},
{"learn":[9.170203312],"iteration":21,"passed_time":0.1882873434,"remaining_time":8.370228267},
{"learn":[9.010299969],"iteration":22,"passed_time":0.1889241926,"remaining_time":8.025171139},
{"learn":[8.843866678],"iteration":23,"passed_time":0.1895300355,"remaining_time":7.707554776},
{"learn":[8.690548059],"iteration":24,"passed_time":0.1901403525,"remaining_time":7.415473746},
{"learn":[8.555307687],"iteration":25,"passed_time":0.1907104431,"remaining_time":7.144306598},
{"learn":[8.413851302],"iteration":26,"passed_time":0.1912869016,"remaining_time":6.893413158},
{"learn":[8.29256019],"iteration":27,"passed_time":0.1918469897,"remaining_time":6.659831214},
{"learn":[8.162193833],"iteration":28,"passed_time":0.1924161092,"remaining_time":6.44262214},
{"learn":[8.040736294],"iteration":29,"passed_time":0.192967055,"remaining_time":6.239268113},
{"learn":[7.921220278],"iteration":30,"passed_time":0.1935293525,"remaining_time":6.049352986},
{"learn":[7.809589039],"iteration":31,"passed_time":0.1940810093,"remaining_time":5.87095053},
{"learn":[7.699675801],"iteration":32,"passed_time":0.1946618067,"remaining_time":5.704180821},
{"learn":[7.60645267],"iteration":33,"passed_time":0.1952240086,"remaining_time":5.546658599},
{"learn":[7.498880302],"iteration":34,"passed_time":0.1960053941,"remaining_time":5.404148724},
{"learn":[7.401158744],"iteration":35,"passed_time":0.1966124306,"remaining_time":5.264843974},
{"learn":[7.306431077],"iteration":36,"passed_time":0.1973505374,"remaining_time":5.136447771},
{"learn":[7.223863468],"iteration":37,"passed_time":0.1981943525,"remaining_time":5.017446503},
{"learn":[7.143477682],"iteration":38,"passed_time":0.1988842657,"remaining_time":4.900712291},
{"learn":[7.062817131],"iteration":39,"passed_time":0.1994798728,"remaining_time":4.787516947},
{"learn":[6.990793435],"iteration":40,"passed_time":0.2000684345,"remaining_time":4.679649479},
{"learn":[6.931862224],"iteration":41,"passed_time":0.2006543918,"remaining_time":4.576831127},
{"learn":[6.858296558],"iteration":42,"passed_time":0.2012457733,"remaining_time":4.478888489},
{"learn":[6.786268161],"iteration":43,"passed_time":0.2018251273,"remaining_time":4.385109584},
{"learn":[6.717118549],"iteration":44,"passed_time":0.2024108853,"remaining_time":4.295608788},
{"learn":[6.652948106],"iteration":45,"passed_time":0.2029993245,"remaining_time":4.21002947},
{"learn":[6.589686076],"iteration":46,"passed_time":0.2035696021,"remaining_time":4.127698527},
{"learn":[6.531283097],"iteration":47,"passed_time":0.2041552943,"remaining_time":4.049080004},
{"learn":[6.471368031],"iteration":48,"passed_time":0.2047318203,"remaining_time":3.973468593},
{"learn":[6.416481395],"iteration":49,"passed_time":0.2053136757,"remaining_time":3.900959838},
{"learn":[6.369870822],"iteration":50,"passed_time":0.2059064071,"remaining_time":3.831474124},
{"learn":[6.325678067],"iteration":51,"passed_time":0.2064871706,"remaining_time":3.764419957},
{"learn":[6.275766122],"iteration":52,"passed_time":0.2070817723,"remaining_time":3.700121478},
{"learn":[6.224773967],"iteration":53,"passed_time":0.2076521809,"remaining_time":3.637758577},
{"learn":[6.182249254],"iteration":54,"passed_time":0.2082292028,"remaining_time":3.577756302},
{"learn":[6.139904173],"iteration":55,"passed_time":0.208862151,"remaining_time":3.520819118},
{"learn":[6.100525536],"iteration":56,"passed_time":0.2094713745,"remaining_time":3.465465021},
{"learn":[6.062568564],"iteration":57,"passed_time":0.2101471626,"remaining_time":3.413079779},
{"learn":[6.030559288],"iteration":58,"passed_time":0.2107737289,"remaining_time":3.361662354},
{"learn":[5.997931376],"iteration":59,"passed_time":0.2113514071,"remaining_time":3.311172044},
{"learn":[5.964103835],"iteration":60,"passed_time":0.2119269748,"remaining_time":3.262285727},
{"learn":[5.933729724],"iteration":61,"passed_time":0.2128109679,"remaining_time":3.219623998},
{"learn":[5.901932711],"iteration":62,"passed_time":0.213581984,"remaining_time":3.176608238},
{"learn":[5.873727795],"iteration":63,"passed_time":0.2142088344,"remaining_time":3.132804203},
{"learn":[5.846485734],"iteration":64,"passed_time":0.2148083879,"remaining_time":3.089936041},
{"learn":[5.820630862],"iteration":65,"passed_time":0.2153889144,"remaining_time":3.048079486},
{"learn":[5.793646238],"iteration":66,"passed_time":0.2159772966,"remaining_time":3.007564444},
{"learn":[5.765388646],"iteration":67,"passed_time":0.2165735348,"remaining_time":2.968331388},
{"learn":[5.747073912],"iteration":68,"passed_time":0.2171690252,"remaining_time":2.930208152},
{"learn":[5.722315217],"iteration":69,"passed_time":0.2177414401,"remaining_time":2.892850562},
{"learn":[5.699970599],"iteration":70,"passed_time":0.2183154941,"remaining_time":2.85655062},
{"learn":[5.682732647],"iteration":71,"passed_time":0.2189139719,"remaining_time":2.82155786},
{"learn":[5.663525791],"iteration":72,"passed_time":0.2194587847,"remaining_time":2.786825937},
{"learn":[5.642381613],"iteration":73,"passed_time":0.2200103265,"remaining_time":2.753102193},
{"learn":[5.621404779],"iteration":74,"passed_time":0.2205496903,"remaining_time":2.720112847},
{"learn":[5.602460129],"iteration":75,"passed_time":0.2210992287,"remaining_time":2.688101149},
{"learn":[5.587337574],"iteration":76,"passed_time":0.2216427478,"remaining_time":2.656834496},
{"learn":[5.572393026],"iteration":77,"passed_time":0.2221787595,"remaining_time":2.626266875},
{"learn":[5.558425806],"iteration":78,"passed_time":0.2227367797,"remaining_time":2.596716128},
{"learn":[5.541518902],"iteration":79,"passed_time":0.2232886768,"remaining_time":2.567819783},
{"learn":[5.526157283],"iteration":80,"passed_time":0.2238771785,"remaining_time":2.540038605},
{"learn":[5.511746977],"iteration":81,"passed_time":0.2246764432,"remaining_time":2.515280181},
{"learn":[5.504975022],"iteration":82,"passed_time":0.2250149667,"remaining_time":2.486008728},
{"learn":[5.493980522],"iteration":83,"passed_time":0.2256438403,"remaining_time":2.460592354},
{"learn":[5.480745463],"iteration":84,"passed_time":0.2262720845,"remaining_time":2.435752439},
{"learn":[5.464052013],"iteration":85,"passed_time":0.2269122391,"remaining_time":2.411602169},
{"learn":[5.449143727],"iteration":86,"passed_time":0.2278549341,"remaining_time":2.391167297},
{"learn":[5.438255432],"iteration":87,"passed_time":0.2285911741,"remaining_time":2.369035804},
{"learn":[5.425927931],"iteration":88,"passed_time":0.2292186953,"remaining_time":2.346272263},
{"learn":[5.412331217],"iteration":89,"passed_time":0.2298545904,"remaining_time":2.324085303},
{"learn":[5.400691499],"iteration":90,"passed_time":0.2304946994,"remaining_time":2.302414086},
{"learn":[5.391618744],"iteration":91,"passed_time":0.2311020845,"remaining_time":2.280877095},
{"learn":[5.380766572],"iteration":92,"passed_time":0.231690891,"remaining_time":2.259609013},
{"learn":[5.372207183],"iteration":93,"passed_time":0.2322583508,"remaining_time":2.238575169},
{"learn":[5.362918837],"iteration":94,"passed_time":0.2328342511,"remaining_time":2.218052602},
{"learn":[5.348292324],"iteration":95,"passed_time":0.233425707,"remaining_time":2.198092074},
{"learn":[5.339772295],"iteration":96,"passed_time":0.2340348783,"remaining_time":2.178695826},
{"learn":[5.331515983],"iteration":97,"passed_time":0.2346121326,"remaining_time":2.159389221},
{"learn":[5.323861644],"iteration":98,"passed_time":0.2351829867,"remaining_time":2.140402738},
{"learn":[5.313277281],"iteration":99,"passed_time":0.2357508775,"remaining_time":2.121757897},
{"learn":[5.30685627],"iteration":100,"passed_time":0.2363138366,"remaining_time":2.10342712},
{"learn":[5.29652059],"iteration":101,"passed_time":0.236896664,"remaining_time":2.085619649},
{"learn":[5.288350766],"iteration":102,"passed_time":0.2374684168,"remaining_time":2.068050193},
{"learn":[5.27993346],"iteration":103,"passed_time":0.2380307312,"remaining_time":2.050726299},
{"learn":[5.271789139],"iteration":104,"passed_time":0.238721546,"remaining_time":2.034816987},
{"learn":[5.262684686],"iteration":105,"passed_time":0.2392975475,"remaining_time":2.018226486},
{"learn":[5.251619772],"iteration":106,"passed_time":0.239885,"remaining_time":2.002030888},
{"learn":[5.241012171],"iteration":107,"passed_time":0.2404529457,"remaining_time":1.985963219},
{"learn":[5.232684032],"iteration":108,"passed_time":0.2410095084,"remaining_time":1.970086899},
{"learn":[5.224267141],"iteration":109,"passed_time":0.2416302064,"remaining_time":1.955008033},
{"learn":[5.216324968],"iteration":110,"passed_time":0.2423646898,"remaining_time":1.941100984},
{"learn":[5.211102527],"iteration":111,"passed_time":0.2431047542,"remaining_time":1.927473408},
{"learn":[5.206364257],"iteration":112,"passed_time":0.2437679453,"remaining_time":1.913470509},
{"learn":[5.196937641],"iteration":113,"passed_time":0.2444774612,"remaining_time":1.900061672},
{"learn":[5.190746047],"iteration":114,"passed_time":0.2452991934,"remaining_time":1.887737271},
{"learn":[5.181885213],"iteration":115,"passed_time":0.2459555666,"remaining_time":1.874351042},
{"learn":[5.178293568],"iteration":116,"passed_time":0.2464134967,"remaining_time":1.859684766},
{"learn":[5.170991438],"iteration":117,"passed_time":0.24697741,"remaining_time":1.846051488},
{"learn":[5.166257212],"iteration":118,"passed_time":0.2475200018,"remaining_time":1.832480014},
{"learn":[5.161421246],"iteration":119,"passed_time":0.248046789,"remaining_time":1.819009786},
{"learn":[5.158223542],"iteration":120,"passed_time":0.2485775449,"remaining_time":1.805782331},
{"learn":[5.15470988],"iteration":121,"passed_time":0.2490213325,"remaining_time":1.792137131},
{"learn":[5.146388143],"iteration":122,"passed_time":0.2496091576,"remaining_time":1.779733587},
{"learn":[5.139529364],"iteration":123,"passed_time":0.2502292951,"remaining_time":1.767748891},
{"learn":[5.134276023],"iteration":124,"passed_time":0.2508028395,"remaining_time":1.755619877},
{"learn":[5.128536065],"iteration":125,"passed_time":0.2514046863,"remaining_time":1.743870602},
{"learn":[5.123300353],"iteration":126,"passed_time":0.2518659027,"remaining_time":1.731330182},
{"learn":[5.116200518],"iteration":127,"passed_time":0.2524794969,"remaining_time":1.720016573},
{"learn":[5.108728704],"iteration":128,"passed_time":0.2530541072,"remaining_time":1.708605638},
{"learn":[5.104075866],"iteration":129,"passed_time":0.2535814994,"remaining_time":1.697045419},
{"learn":[5.100317606],"iteration":130,"passed_time":0.2541120184,"remaining_time":1.685674381},
{"learn":[5.095814182],"iteration":131,"passed_time":0.2546410302,"remaining_time":1.674457683},
{"learn":[5.092146915],"iteration":132,"passed_time":0.2552004169,"remaining_time":1.66359971},
{"learn":[5.085258329],"iteration":133,"passed_time":0.2557237494,"remaining_time":1.65266244},
{"learn":[5.079219421],"iteration":134,"passed_time":0.2562838598,"remaining_time":1.642115102},
{"learn":[5.076476829],"iteration":135,"passed_time":0.2570577995,"remaining_time":1.633073079},
{"learn":[5.072133867],"iteration":136,"passed_time":0.2576897895,"remaining_time":1.623257579},
{"learn":[5.067031564],"iteration":137,"passed_time":0.2582375512,"remaining_time":1.613049051},
{"learn":[5.061358312],"iteration":138,"passed_time":0.2588438605,"remaining_time":1.603342186},
{"learn":[5.056759124],"iteration":139,"passed_time":0.2595839877,"remaining_time":1.594587353},
{"learn":[5.050254],"iteration":140,"passed_time":0.260209377,"remaining_time":1.585247197},
{"learn":[5.048376474],"iteration":141,"passed_time":0.2605871107,"remaining_time":1.574533387},
{"learn":[5.042603751],"iteration":142,"passed_time":0.2611214577,"remaining_time":1.564902722},
{"learn":[5.037477349],"iteration":143,"passed_time":0.2616806405,"remaining_time":1.55554603},
{"learn":[5.03230489],"iteration":144,"passed_time":0.262215452,"remaining_time":1.546166976},
{"learn":[5.025976187],"iteration":145,"passed_time":0.2627526966,"remaining_time":1.536923308},
{"learn":[5.01952451],"iteration":146,"passed_time":0.2632721845,"remaining_time":1.527695057},
{"learn":[5.017569424],"iteration":147,"passed_time":0.2637985552,"remaining_time":1.518624115},
{"learn":[5.008962367],"iteration":148,"passed_time":0.2643199157,"remaining_time":1.50963925},
{"learn":[5.003880266],"iteration":149,"passed_time":0.2648538173,"remaining_time":1.500838298},
{"learn":[4.996387564],"iteration":150,"passed_time":0.2653850137,"remaining_time":1.492131633},
{"learn":[4.993361683],"iteration":151,"passed_time":0.2659119663,"remaining_time":1.483508865},
{"learn":[4.99005752],"iteration":152,"passed_time":0.2664333062,"remaining_time":1.474960852},
{"learn":[4.986908764],"iteration":153,"passed_time":0.2671947255,"remaining_time":1.46783596},
{"learn":[4.985207175],"iteration":154,"passed_time":0.2677774854,"remaining_time":1.459819195},
{"learn":[4.979003494],"iteration":155,"passed_time":0.2683918419,"remaining_time":1.452068683},
{"learn":[4.973142217],"iteration":156,"passed_time":0.269013994,"remaining_time":1.444450936},
{"learn":[4.967056696],"iteration":157,"passed_time":0.2696288173,"remaining_time":1.436882685},
{"learn":[4.961460696],"iteration":158,"passed_time":0.2702194672,"remaining_time":1.429274037},
{"learn":[4.954240363],"iteration":159,"passed_time":0.2708038777,"remaining_time":1.421720358},
{"learn":[4.952320707],"iteration":160,"passed_time":0.2712019701,"remaining_time":1.413282316},
{"learn":[4.948337777],"iteration":161,"passed_time":0.2720250589,"remaining_time":1.407141971},
{"learn":[4.943228639],"iteration":162,"passed_time":0.2726954364,"remaining_time":1.400282701},
{"learn":[4.938545759],"iteration":163,"passed_time":0.2733395238,"remaining_time":1.393364889},
{"learn":[4.935330572],"iteration":164,"passed_time":0.2739716846,"remaining_time":1.386462767},
{"learn":[4.932051543],"iteration":165,"passed_time":0.2746024008,"remaining_time":1.379628929},
{"learn":[4.928964153],"iteration":166,"passed_time":0.275189512,"remaining_time":1.372651877},
{"learn":[4.922860227],"iteration":167,"passed_time":0.2757777477,"remaining_time":1.365756465},
{"learn":[4.917668772],"iteration":168,"passed_time":0.2763841142,"remaining_time":1.359024845},
{"learn":[4.910365386],"iteration":169,"passed_time":0.2770073035,"remaining_time":1.352447423},
{"learn":[4.906457206],"iteration":170,"passed_time":0.2775849305,"remaining_time":1.345718756},
{"learn":[4.901996508],"iteration":171,"passed_time":0.2781783112,"remaining_time":1.339137452},
{"learn":[4.896816173],"iteration":172,"passed_time":0.2787601993,"remaining_time":1.332570432},
{"learn":[4.891123132],"iteration":173,"passed_time":0.2793336647,"remaining_time":1.326032225},
{"learn":[4.887630202],"iteration":174,"passed_time":0.2798879023,"remaining_time":1.319471539},
{"learn":[4.885259712],"iteration":175,"passed_time":0.2805498489,"remaining_time":1.313483384},
{"learn":[4.880659728],"iteration":176,"passed_time":0.2811359341,"remaining_time":1.307202677},
{"learn":[4.877299723],"iteration":177,"passed_time":0.2817024811,"remaining_time":1.300895727},
{"learn":[4.874038772],"iteration":178,"passed_time":0.2822751272,"remaining_time":1.294680891},
{"learn":[4.86943698],"iteration":179,"passed_time":0.2828276472,"remaining_time":1.288437059},
{"learn":[4.861268711],"iteration":180,"passed_time":0.2833905348,"remaining_time":1.282303028},
{"learn":[4.858673056],"iteration":181,"passed_time":0.2839376529,"remaining_time":1.276159341},
{"learn":[4.854036207],"iteration":182,"passed_time":0.2844877707,"remaining_time":1.270090211},
{"learn":[4.85130244],"iteration":183,"passed_time":0.2850307145,"remaining_time":1.264049256},
{"learn":[4.847510084],"iteration":184,"passed_time":0.2856597636,"remaining_time":1.258447066},
{"learn":[4.845691673],"iteration":185,"passed_time":0.2863050941,"remaining_time":1.252969605},
{"learn":[4.842058646],"iteration":186,"passed_time":0.2869908012,"remaining_time":1.247719366},
{"learn":[4.838623675],"iteration":187,"passed_time":0.2875873624,"remaining_time":1.24213265},
{"learn":[4.834602161],"iteration":188,"passed_time":0.2881699775,"remaining_time":1.236538898},
{"learn":[4.830858976],"iteration":189,"passed_time":0.2887275854,"remaining_time":1.230891285},
{"learn":[4.827590511],"iteration":190,"passed_time":0.2892841286,"remaining_time":1.225292461},
{"learn":[4.822246226],"iteration":191,"passed_time":0.2898413498,"remaining_time":1.219749014},
{"learn":[4.816686395],"iteration":192,"passed_time":0.2904081267,"remaining_time":1.214297193},
{"learn":[4.814797121],"iteration":193,"passed_time":0.2910078556,"remaining_time":1.209032637},
{"learn":[4.811639392],"iteration":194,"passed_time":0.2915709417,"remaining_time":1.203664657},
{"learn":[4.804813432],"iteration":195,"passed_time":0.2921310373,"remaining_time":1.198333439},
{"learn":[4.80251613],"iteration":196,"passed_time":0.292685312,"remaining_time":1.193026932},
{"learn":[4.800087884],"iteration":197,"passed_time":0.293232737,"remaining_time":1.187740682},
{"learn":[4.794773135],"iteration":198,"passed_time":0.2937801475,"remaining_time":1.182502001},
{"learn":[4.791664833],"iteration":199,"passed_time":0.2944196751,"remaining_time":1.1776787},
{"learn":[4.785989873],"iteration":200,"passed_time":0.2950061163,"remaining_time":1.172686005},
{"learn":[4.782387142],"iteration":201,"passed_time":0.2955980511,"remaining_time":1.167758638},
{"learn":[4.778623704],"iteration":202,"passed_time":0.2961752393,"remaining_time":1.162816087},
{"learn":[4.775772178],"iteration":203,"passed_time":0.296741984,"remaining_time":1.157875585},
{"learn":[4.77023101],"iteration":204,"passed_time":0.2975900429,"remaining_time":1.154068703},
{"learn":[4.764496689],"iteration":205,"passed_time":0.2981686624,"remaining_time":1.149252029},
{"learn":[4.763138716],"iteration":206,"passed_time":0.2987344902,"remaining_time":1.144427298},
{"learn":[4.758053283],"iteration":207,"passed_time":0.2993162269,"remaining_time":1.139704095},
{"learn":[4.755063788],"iteration":208,"passed_time":0.2998821957,"remaining_time":1.134960846},
{"learn":[4.752465267],"iteration":209,"passed_time":0.3004393916,"remaining_time":1.130224378},
{"learn":[4.748067377],"iteration":210,"passed_time":0.3013250035,"remaining_time":1.126755582},
{"learn":[4.744163298],"iteration":211,"passed_time":0.3019476155,"remaining_time":1.12233359},
{"learn":[4.736670896],"iteration":212,"passed_time":0.3025202153,"remaining_time":1.117762486},
{"learn":[4.73349255],"iteration":213,"passed_time":0.3030836149,"remaining_time":1.11319496},
{"learn":[4.731864595],"iteration":214,"passed_time":0.303651112,"remaining_time":1.108679641},
{"learn":[4.728398311],"iteration":215,"passed_time":0.3042093455,"remaining_time":1.104167254},
{"learn":[4.723865975],"iteration":216,"passed_time":0.3047697293,"remaining_time":1.099699069},
{"learn":[4.723483365],"iteration":217,"passed_time":0.3053085423,"remaining_time":1.095189358},
{"learn":[4.72095416],"iteration":218,"passed_time":0.3058517285,"remaining_time":1.090731506},
{"learn":[4.716173382],"iteration":219,"passed_time":0.306414497,"remaining_time":1.086378671},
{"learn":[4.710563974],"iteration":220,"passed_time":0.306981824,"remaining_time":1.082076203},
{"learn":[4.707160263],"iteration":221,"passed_time":0.3075253162,"remaining_time":1.077723856},
{"learn":[4.70408351],"iteration":222,"passed_time":0.308179921,"remaining_time":1.073792819},
{"learn":[4.702501831],"iteration":223,"passed_time":0.3087747034,"remaining_time":1.069683794},
{"learn":[4.700269738],"iteration":224,"passed_time":0.3093709713,"remaining_time":1.065611123},
{"learn":[4.695346302],"iteration":225,"passed_time":0.3099431902,"remaining_time":1.061486855},
{"learn":[4.689769299],"iteration":226,"passed_time":0.3105017485,"remaining_time":1.057347364},
{"learn":[4.687919514],"iteration":227,"passed_time":0.3110607211,"remaining_time":1.053240687},
{"learn":[4.682982074],"iteration":228,"passed_time":0.3116203468,"remaining_time":1.049167194},
{"learn":[4.679578702],"iteration":229,"passed_time":0.3121732183,"remaining_time":1.045101644},
{"learn":[4.675751423],"iteration":230,"passed_time":0.312723739,"remaining_time":1.041058681},
{"learn":[4.672710726],"iteration":231,"passed_time":0.3132828436,"remaining_time":1.037074241},
{"learn":[4.6690533],"iteration":232,"passed_time":0.3138291858,"remaining_time":1.033077191},
{"learn":[4.667595702],"iteration":233,"passed_time":0.3143825126,"remaining_time":1.029132499},
{"learn":[4.664241291],"iteration":234,"passed_time":0.3149349225,"remaining_time":1.025213684},
{"learn":[4.662246999],"iteration":235,"passed_time":0.3157817038,"remaining_time":1.022276363},
{"learn":[4.658668443],"iteration":236,"passed_time":0.3165456336,"remaining_time":1.019089951},
{"learn":[4.658017572],"iteration":237,"passed_time":0.3171413019,"remaining_time":1.015385177},
{"learn":[4.657656705],"iteration":238,"passed_time":0.3176808824,"remaining_time":1.011527831},
{"learn":[4.653242871],"iteration":239,"passed_time":0.318256008,"remaining_time":1.007810692},
{"learn":[4.6507302],"iteration":240,"passed_time":0.3187924838,"remaining_time":1.003997905},
{"learn":[4.647671336],"iteration":241,"passed_time":0.3193240334,"remaining_time":1.000196766},
{"learn":[4.645506007],"iteration":242,"passed_time":0.3198479023,"remaining_time":0.9963986092},
{"learn":[4.641297906],"iteration":243,"passed_time":0.3203987203,"remaining_time":0.9927107892},
{"learn":[4.63798107],"iteration":244,"passed_time":0.3209419408,"remaining_time":0.9890251645},
{"learn":[4.635062318],"iteration":245,"passed_time":0.3214686295,"remaining_time":0.9853144174},
{"learn":[4.631606017],"iteration":246,"passed_time":0.3221869113,"remaining_time":0.9822135392},
{"learn":[4.630215494],"iteration":247,"passed_time":0.3227568939,"remaining_time":0.9786821945},
{"learn":[4.62729814],"iteration":248,"passed_time":0.323306975,"remaining_time":0.9751146112},
{"learn":[4.624691756],"iteration":249,"passed_time":0.3238554091,"remaining_time":0.9715662273},
{"learn":[4.621840053],"iteration":250,"passed_time":0.3244037034,"remaining_time":0.9680413302},
{"learn":[4.619602091],"iteration":251,"passed_time":0.3249412541,"remaining_time":0.964508167},
{"learn":[4.613584029],"iteration":252,"passed_time":0.3254907197,"remaining_time":0.9610338642},
{"learn":[4.6119388],"iteration":253,"passed_time":0.326051458,"remaining_time":0.9576156994},
{"learn":[4.60870702],"iteration":254,"passed_time":0.3265913814,"remaining_time":0.9541591338},
{"learn":[4.604771557],"iteration":255,"passed_time":0.327181592,"remaining_time":0.9508715017},
{"learn":[4.604231277],"iteration":256,"passed_time":0.3277705701,"remaining_time":0.9476012981},
{"learn":[4.600750354],"iteration":257,"passed_time":0.3283326931,"remaining_time":0.9442746444},
{"learn":[4.596488253],"iteration":258,"passed_time":0.3288910974,"remaining_time":0.9409586996},
{"learn":[4.59470784],"iteration":259,"passed_time":0.3294530471,"remaining_time":0.9376740571},
{"learn":[4.588818005],"iteration":260,"passed_time":0.3300250625,"remaining_time":0.9344387785},
{"learn":[4.585054174],"iteration":261,"passed_time":0.3308471463,"remaining_time":0.9319282211},
{"learn":[4.581471435],"iteration":262,"passed_time":0.3315276691,"remaining_time":0.9290338102},
{"learn":[4.577555199],"iteration":263,"passed_time":0.3321496623,"remaining_time":0.925992998},
{"learn":[4.57457145],"iteration":264,"passed_time":0.3327177024,"remaining_time":0.9228207972},
{"learn":[4.573029224],"iteration":265,"passed_time":0.3332796231,"remaining_time":0.9196512907},
{"learn":[4.571326203],"iteration":266,"passed_time":0.3340824773,"remaining_time":0.9171627559},
{"learn":[4.571019224],"iteration":267,"passed_time":0.3347947335,"remaining_time":0.9144393467},
{"learn":[4.565766631],"iteration":268,"passed_time":0.3355342763,"remaining_time":0.9118050408},
{"learn":[4.563383471],"iteration":269,"passed_time":0.3361151945,"remaining_time":0.9087558963},
{"learn":[4.558165805],"iteration":270,"passed_time":0.3366735046,"remaining_time":0.9056641508},
{"learn":[4.55629209],"iteration":271,"passed_time":0.3372225653,"remaining_time":0.9025662778},
{"learn":[4.549383848],"iteration":272,"passed_time":0.3377810454,"remaining_time":0.8995121612},
{"learn":[4.546227503],"iteration":273,"passed_time":0.3383283645,"remaining_time":0.8964466885},
{"learn":[4.540620977],"iteration":274,"passed_time":0.3388788281,"remaining_time":0.8934078196},
{"learn":[4.532898237],"iteration":275,"passed_time":0.3394397901,"remaining_time":0.8904145219},
{"learn":[4.529757367],"iteration":276,"passed_time":0.3399979761,"remaining_time":0.8874315406},
{"learn":[4.52579294],"iteration":277,"passed_time":0.3405892149,"remaining_time":0.8845518459},
{"learn":[4.521572155],"iteration":278,"passed_time":0.3411789325,"remaining_time":0.881684625},
{"learn":[4.518818099],"iteration":279,"passed_time":0.3417323553,"remaining_time":0.8787403423},
{"learn":[4.514012334],"iteration":280,"passed_time":0.34229335,"remaining_time":0.8758324507},
{"learn":[4.508331416],"iteration":281,"passed_time":0.3428518702,"remaining_time":0.8729349035},
{"learn":[4.506038537],"iteration":282,"passed_time":0.3434013544,"remaining_time":0.8700309933},
{"learn":[4.505805643],"iteration":283,"passed_time":0.3439291615,"remaining_time":0.8670890127},
{"learn":[4.501550352],"iteration":284,"passed_time":0.3445224111,"remaining_time":0.8643281542},
{"learn":[4.494692643],"iteration":285,"passed_time":0.3451154333,"remaining_time":0.8615818858},
{"learn":[4.489330245],"iteration":286,"passed_time":0.3458558281,"remaining_time":0.8592167436},
{"learn":[4.484826955],"iteration":287,"passed_time":0.3466132009,"remaining_time":0.8569048577},
{"learn":[4.478285428],"iteration":288,"passed_time":0.3473415703,"remaining_time":0.8545323755},
{"learn":[4.475311671],"iteration":289,"passed_time":0.3479310104,"remaining_time":0.8518310945},
{"learn":[4.471581298],"iteration":290,"passed_time":0.3485033766,"remaining_time":0.8491027285},
{"learn":[4.469164956],"iteration":291,"passed_time":0.3492165473,"remaining_time":0.8467305324},
{"learn":[4.462068024],"iteration":292,"passed_time":0.3498030919,"remaining_time":0.8440641159},
{"learn":[4.458540976],"iteration":293,"passed_time":0.3503908396,"remaining_time":0.8414147373},
{"learn":[4.455757458],"iteration":294,"passed_time":0.3509957258,"remaining_time":0.8388202939},
{"learn":[4.453027414],"iteration":295,"passed_time":0.351566759,"remaining_time":0.8361587781},
{"learn":[4.450659338],"iteration":296,"passed_time":0.352185822,"remaining_time":0.8336250265},
{"learn":[4.444696901],"iteration":297,"passed_time":0.3528741169,"remaining_time":0.8312672149},
{"learn":[4.442052813],"iteration":298,"passed_time":0.3534444916,"remaining_time":0.8286441091},
{"learn":[4.440036756],"iteration":299,"passed_time":0.353995789,"remaining_time":0.8259901743},
{"learn":[4.435017051],"iteration":300,"passed_time":0.3545694162,"remaining_time":0.8234020661},
{"learn":[4.429962125],"iteration":301,"passed_time":0.3551369913,"remaining_time":0.8208133111},
{"learn":[4.427666256],"iteration":302,"passed_time":0.3556989774,"remaining_time":0.8182250403},
{"learn":[4.425030004],"iteration":303,"passed_time":0.3562620904,"remaining_time":0.8156526807},
{"learn":[4.422588771],"iteration":304,"passed_time":0.3568100051,"remaining_time":0.813058864},
{"learn":[4.418936667],"iteration":305,"passed_time":0.3573597809,"remaining_time":0.8104826403},
{"learn":[4.416887976],"iteration":306,"passed_time":0.3579046706,"remaining_time":0.8079085887},
{"learn":[4.413773354],"iteration":307,"passed_time":0.3585090775,"remaining_time":0.8054814338},
{"learn":[4.411129391],"iteration":308,"passed_time":0.3591380504,"remaining_time":0.8031210123},
{"learn":[4.40850819],"iteration":309,"passed_time":0.3597149945,"remaining_time":0.8006559555},
{"learn":[4.404880292],"iteration":310,"passed_time":0.3606201022,"remaining_time":0.7989300658},
{"learn":[4.404593827],"iteration":311,"passed_time":0.361255056,"remaining_time":0.7966137132},
{"learn":[4.402139942],"iteration":312,"passed_time":0.3618481104,"remaining_time":0.7942161401},
{"learn":[4.400284725],"iteration":313,"passed_time":0.3624768215,"remaining_time":0.7919079604},
{"learn":[4.395805521],"iteration":314,"passed_time":0.3631057216,"remaining_time":0.789610855},
{"learn":[4.392838833],"iteration":315,"passed_time":0.3637010024,"remaining_time":0.7872515368},
{"learn":[4.389213061],"iteration":316,"passed_time":0.3643420648,"remaining_time":0.7850019881},
{"learn":[4.3861981],"iteration":317,"passed_time":0.3649753046,"remaining_time":0.7827457791},
{"learn":[4.385054234],"iteration":318,"passed_time":0.3655534005,"remaining_time":0.7803820244},
{"learn":[4.379364607],"iteration":319,"passed_time":0.3661491143,"remaining_time":0.7780668679},
{"learn":[4.378387619],"iteration":320,"passed_time":0.3668504941,"remaining_time":0.7759859362},
{"learn":[4.375816727],"iteration":321,"passed_time":0.3674886829,"remaining_time":0.7737805187},
{"learn":[4.374600202],"iteration":322,"passed_time":0.368014135,"remaining_time":0.7713485121},
{"learn":[4.37098897],"iteration":323,"passed_time":0.3685522441,"remaining_time":0.768954682},
{"learn":[4.367418484],"iteration":324,"passed_time":0.369099643,"remaining_time":0.7665915662},
{"learn":[4.363584638],"iteration":325,"passed_time":0.3696448483,"remaining_time":0.7642350544},
{"learn":[4.360770706],"iteration":326,"passed_time":0.3701920408,"remaining_time":0.7618937109},
{"learn":[4.358675808],"iteration":327,"passed_time":0.3708294897,"remaining_time":0.7597482228},
{"learn":[4.354228195],"iteration":328,"passed_time":0.371505045,"remaining_time":0.7576896206},
{"learn":[4.353773425],"iteration":329,"passed_time":0.3721215707,"remaining_time":0.7555195526},
{"learn":[4.351648009],"iteration":330,"passed_time":0.3727104562,"remaining_time":0.7533030066},
{"learn":[4.348209927],"iteration":331,"passed_time":0.3732622097,"remaining_time":0.7510215545},
{"learn":[4.345852733],"iteration":332,"passed_time":0.3738153628,"remaining_time":0.7487532943},
{"learn":[4.34237339],"iteration":333,"passed_time":0.3743845866,"remaining_time":0.7465273493},
{"learn":[4.340814362],"iteration":334,"passed_time":0.3757141485,"remaining_time":0.7458206232},
{"learn":[4.339707068],"iteration":335,"passed_time":0.3765516234,"remaining_time":0.7441377319},
{"learn":[4.335430786],"iteration":336,"passed_time":0.3773114033,"remaining_time":0.742307004},
{"learn":[4.33521887],"iteration":337,"passed_time":0.3778733128,"remaining_time":0.7400950682},
{"learn":[4.328507238],"iteration":338,"passed_time":0.3786014105,"remaining_time":0.7382169096},
{"learn":[4.326140732],"iteration":339,"passed_time":0.3794238193,"remaining_time":0.7365285905},
{"learn":[4.323785636],"iteration":340,"passed_time":0.3801304095,"remaining_time":0.7346215245},
{"learn":[4.320632534],"iteration":341,"passed_time":0.3807673501,"remaining_time":0.7325874747},
{"learn":[4.31973724],"iteration":342,"passed_time":0.3813697308,"remaining_time":0.7304953736},
{"learn":[4.318000924],"iteration":343,"passed_time":0.3820610713,"remaining_time":0.7285815778},
{"learn":[4.312713628],"iteration":344,"passed_time":0.3827547287,"remaining_time":0.7266792675},
{"learn":[4.308220789],"iteration":345,"passed_time":0.3833656648,"remaining_time":0.724627586},
{"learn":[4.305890947],"iteration":346,"passed_time":0.3839774194,"remaining_time":0.7225857489},
{"learn":[4.305137856],"iteration":347,"passed_time":0.384586202,"remaining_time":0.7205465623},
{"learn":[4.304787172],"iteration":348,"passed_time":0.3851734319,"remaining_time":0.7184753701},
{"learn":[4.30350134],"iteration":349,"passed_time":0.3857301485,"remaining_time":0.71635599},
{"learn":[4.30293809],"iteration":350,"passed_time":0.3862635798,"remaining_time":0.7142024596},
{"learn":[4.299548459],"iteration":351,"passed_time":0.386804043,"remaining_time":0.7120710791},
{"learn":[4.294768408],"iteration":352,"passed_time":0.3873708423,"remaining_time":0.7099969829},
{"learn":[4.294581479],"iteration":353,"passed_time":0.3879049065,"remaining_time":0.7078716655},
{"learn":[4.292551604],"iteration":354,"passed_time":0.3884488466,"remaining_time":0.7057732565},
{"learn":[4.288628894],"iteration":355,"passed_time":0.3890494456,"remaining_time":0.7037860758},
{"learn":[4.287802767],"iteration":356,"passed_time":0.3896280482,"remaining_time":0.7017670448},
{"learn":[4.284566905],"iteration":357,"passed_time":0.3905022162,"remaining_time":0.7002860972},
{"learn":[4.27890232],"iteration":358,"passed_time":0.3911314596,"remaining_time":0.6983712133},
{"learn":[4.276938023],"iteration":359,"passed_time":0.3917185505,"remaining_time":0.6963885343},
{"learn":[4.273425094],"iteration":360,"passed_time":0.3925611348,"remaining_time":0.6948658314},
{"learn":[4.269726505],"iteration":361,"passed_time":0.3931531151,"remaining_time":0.692905214},
{"learn":[4.265565857],"iteration":362,"passed_time":0.3937132479,"remaining_time":0.6908962504},
{"learn":[4.262117173],"iteration":363,"passed_time":0.3942947377,"remaining_time":0.6889325637},
{"learn":[4.259185148],"iteration":364,"passed_time":0.3948821926,"remaining_time":0.6869868282},
{"learn":[4.257668507],"iteration":365,"passed_time":0.3955309232,"remaining_time":0.6851546594},
{"learn":[4.253432436],"iteration":366,"passed_time":0.3961777596,"remaining_time":0.6833256726},
{"learn":[4.250216667],"iteration":367,"passed_time":0.3967170073,"remaining_time":0.6813183386},
{"learn":[4.24514828],"iteration":368,"passed_time":0.3972761908,"remaining_time":0.6793530526},
{"learn":[4.244015772],"iteration":369,"passed_time":0.3977923874,"remaining_time":0.6773221731},
{"learn":[4.240329192],"iteration":370,"passed_time":0.3983360372,"remaining_time":0.6753460037},
{"learn":[4.236718014],"iteration":371,"passed_time":0.3988704463,"remaining_time":0.6733619362},
{"learn":[4.233495944],"iteration":372,"passed_time":0.3994018056,"remaining_time":0.6713805151},
{"learn":[4.230357491],"iteration":373,"passed_time":0.3999448421,"remaining_time":0.6694263934},
{"learn":[4.227381215],"iteration":374,"passed_time":0.400479228,"remaining_time":0.66746538},
{"learn":[4.226169067],"iteration":375,"passed_time":0.4009952893,"remaining_time":0.6654815439},
{"learn":[4.225963861],"iteration":376,"passed_time":0.4016195076,"remaining_time":0.6636842262},
{"learn":[4.224346548],"iteration":377,"passed_time":0.4022166156,"remaining_time":0.661848505},
{"learn":[4.222595381],"iteration":378,"passed_time":0.4027689833,"remaining_time":0.6599460123},
{"learn":[4.219700938],"iteration":379,"passed_time":0.4034134462,"remaining_time":0.6582008859},
{"learn":[4.216356207],"iteration":380,"passed_time":0.4043811176,"remaining_time":0.6569866451},
{"learn":[4.214326494],"iteration":381,"passed_time":0.4051043937,"remaining_time":0.6553783124},
{"learn":[4.212901398],"iteration":382,"passed_time":0.4056991306,"remaining_time":0.6535675289},
{"learn":[4.211331091],"iteration":383,"passed_time":0.4063160513,"remaining_time":0.6517986656},
{"learn":[4.208624791],"iteration":384,"passed_time":0.4069213871,"remaining_time":0.6500172806},
{"learn":[4.204659106],"iteration":385,"passed_time":0.4075933181,"remaining_time":0.6483479205},
{"learn":[4.202968852],"iteration":386,"passed_time":0.4082123344,"remaining_time":0.6465998992},
{"learn":[4.197261935],"iteration":387,"passed_time":0.408817994,"remaining_time":0.6448366297},
{"learn":[4.196934403],"iteration":388,"passed_time":0.4093704072,"remaining_time":0.6429956782},
{"learn":[4.192479929],"iteration":389,"passed_time":0.409935393,"remaining_time":0.6411809992},
{"learn":[4.190243116],"iteration":390,"passed_time":0.4104870659,"remaining_time":0.6393519773},
{"learn":[4.185852431],"iteration":391,"passed_time":0.411057929,"remaining_time":0.6375592369},
{"learn":[4.180967944],"iteration":392,"passed_time":0.41160226,"remaining_time":0.6357317349},
{"learn":[4.178283162],"iteration":393,"passed_time":0.4121612947,"remaining_time":0.6339333619},
{"learn":[4.176341157],"iteration":394,"passed_time":0.4127302939,"remaining_time":0.632156526},
{"learn":[4.176041504],"iteration":395,"passed_time":0.413376153,"remaining_time":0.6305030212},
{"learn":[4.175564513],"iteration":396,"passed_time":0.4140175342,"remaining_time":0.6288477913},
{"learn":[4.170830274],"iteration":397,"passed_time":0.4146266919,"remaining_time":0.6271489159},
{"learn":[4.167804808],"iteration":398,"passed_time":0.4151804729,"remaining_time":0.6253720907},
{"learn":[4.165860548],"iteration":399,"passed_time":0.4157310696,"remaining_time":0.6235966045},
{"learn":[4.160950571],"iteration":400,"passed_time":0.4162851649,"remaining_time":0.6218324533},
{"learn":[4.158544115],"iteration":401,"passed_time":0.416833094,"remaining_time":0.6200651499},
{"learn":[4.154448767],"iteration":402,"passed_time":0.4174608328,"remaining_time":0.618422127},
{"learn":[4.15197457],"iteration":403,"passed_time":0.4180195743,"remaining_time":0.6166823423},
{"learn":[4.149562679],"iteration":404,"passed_time":0.4185845431,"remaining_time":0.6149575386},
{"learn":[4.149327961],"iteration":405,"passed_time":0.4193044142,"remaining_time":0.6134650789},
{"learn":[4.147444889],"iteration":406,"passed_time":0.4200767542,"remaining_time":0.612052863},
{"learn":[4.147254809],"iteration":407,"passed_time":0.4207809443,"remaining_time":0.6105448996},
{"learn":[4.144589165],"iteration":408,"passed_time":0.4213825318,"remaining_time":0.6088926071},
{"learn":[4.141691034],"iteration":409,"passed_time":0.4219801104,"remaining_time":0.6072396711},
{"learn":[4.138893468],"iteration":410,"passed_time":0.4225592022,"remaining_time":0.6055653774},
{"learn":[4.136964597],"iteration":411,"passed_time":0.4231212015,"remaining_time":0.603872006},
{"learn":[4.133773523],"iteration":412,"passed_time":0.4237065401,"remaining_time":0.6022172858},
{"learn":[4.131363444],"iteration":413,"passed_time":0.4242596122,"remaining_time":0.6005220597},
{"learn":[4.130228592],"iteration":414,"passed_time":0.4247949874,"remaining_time":0.5988073919},
{"learn":[4.12884186],"iteration":415,"passed_time":0.4253236386,"remaining_time":0.5970889542},
{"learn":[4.12413494],"iteration":416,"passed_time":0.4259633973,"remaining_time":0.5955315603},
{"learn":[4.119422508],"iteration":417,"passed_time":0.4266354206,"remaining_time":0.5940234803},
{"learn":[4.117038244],"iteration":418,"passed_time":0.4272518541,"remaining_time":0.5924423084},
{"learn":[4.116067631],"iteration":419,"passed_time":0.4278226382,"remaining_time":0.5908026909},
{"learn":[4.110343455],"iteration":420,"passed_time":0.4283920001,"remaining_time":0.5891661949},
{"learn":[4.105604544],"iteration":421,"passed_time":0.4289561235,"remaining_time":0.5875275815},
{"learn":[4.103390131],"iteration":422,"passed_time":0.4295055478,"remaining_time":0.5858739978},
{"learn":[4.096724402],"iteration":423,"passed_time":0.4300634199,"remaining_time":0.5842370987},
{"learn":[4.093431279],"iteration":424,"passed_time":0.4306324356,"remaining_time":0.5826203541},
{"learn":[4.091412744],"iteration":425,"passed_time":0.4312095968,"remaining_time":0.5810195037},
{"learn":[4.091192901],"iteration":426,"passed_time":0.431983226,"remaining_time":0.5796870925},
{"learn":[4.088994581],"iteration":427,"passed_time":0.4326548137,"remaining_time":0.5782209193},
{"learn":[4.087845355],"iteration":428,"passed_time":0.4332510325,"remaining_time":0.5766581341},
{"learn":[4.083650279],"iteration":429,"passed_time":0.4340224948,"remaining_time":0.5753321443},
{"learn":[4.079840652],"iteration":430,"passed_time":0.4347496186,"remaining_time":0.5739501925},
{"learn":[4.075707828],"iteration":431,"passed_time":0.4353709563,"remaining_time":0.5724321833},
{"learn":[4.071345409],"iteration":432,"passed_time":0.4359891885,"remaining_time":0.5709142491},
{"learn":[4.067460475],"iteration":433,"passed_time":0.4366215255,"remaining_time":0.5694188558},
{"learn":[4.064914749],"iteration":434,"passed_time":0.4371990556,"remaining_time":0.5678562446},
{"learn":[4.063823175],"iteration":435,"passed_time":0.4377644463,"remaining_time":0.5662824488},
{"learn":[4.058898471],"iteration":436,"passed_time":0.4383597539,"remaining_time":0.5647518111},
{"learn":[4.054120355],"iteration":437,"passed_time":0.4389978728,"remaining_time":0.5632803756},
{"learn":[4.052715901],"iteration":438,"passed_time":0.4395956321,"remaining_time":0.5617611609},
{"learn":[4.052114167],"iteration":439,"passed_time":0.4401427333,"remaining_time":0.5601816605},
{"learn":[4.051377267],"iteration":440,"passed_time":0.4407009846,"remaining_time":0.558620976},
{"learn":[4.049275336],"iteration":441,"passed_time":0.4412558789,"remaining_time":0.5570605893},
{"learn":[4.047099198],"iteration":442,"passed_time":0.4418172529,"remaining_time":0.555512889},
{"learn":[4.044348685],"iteration":443,"passed_time":0.4423697897,"remaining_time":0.5539585655},
{"learn":[4.042822379],"iteration":444,"passed_time":0.4429176734,"remaining_time":0.552402941},
{"learn":[4.041258611],"iteration":445,"passed_time":0.4434801326,"remaining_time":0.5508699405},
{"learn":[4.040044254],"iteration":446,"passed_time":0.4440643243,"remaining_time":0.5493681685},
{"learn":[4.036860137],"iteration":447,"passed_time":0.4446826462,"remaining_time":0.5479125462},
{"learn":[4.036372284],"iteration":448,"passed_time":0.4452618902,"remaining_time":0.5464126983},
{"learn":[4.03368231],"iteration":449,"passed_time":0.4458813346,"remaining_time":0.5449660756},
{"learn":[4.032439519],"iteration":450,"passed_time":0.4464432735,"remaining_time":0.54345312},
{"learn":[4.032008634],"iteration":451,"passed_time":0.4469913883,"remaining_time":0.5419276124},
{"learn":[4.030034932],"iteration":452,"passed_time":0.4475373116,"remaining_time":0.5404037736},
{"learn":[4.028173412],"iteration":453,"passed_time":0.4480759984,"remaining_time":0.5388755399},
{"learn":[4.023806097],"iteration":454,"passed_time":0.4488413372,"remaining_time":0.5376231402},
{"learn":[4.020239186],"iteration":455,"passed_time":0.4496017214,"remaining_time":0.5363669658},
{"learn":[4.017384838],"iteration":456,"passed_time":0.4503690632,"remaining_time":0.5351212283},
{"learn":[4.016468229],"iteration":457,"passed_time":0.4511583709,"remaining_time":0.5339035743},
{"learn":[4.014530169],"iteration":458,"passed_time":0.4518616168,"remaining_time":0.5325863501},
{"learn":[4.012884822],"iteration":459,"passed_time":0.4524930832,"remaining_time":0.5311875324},
{"learn":[4.008924707],"iteration":460,"passed_time":0.4530606443,"remaining_time":0.529717326},
{"learn":[4.008286778],"iteration":461,"passed_time":0.4536280632,"remaining_time":0.5282508614},
{"learn":[4.006444202],"iteration":462,"passed_time":0.4542070471,"remaining_time":0.5268016939},
{"learn":[4.003284363],"iteration":463,"passed_time":0.454784255,"remaining_time":0.5253542256},
{"learn":[3.999811484],"iteration":464,"passed_time":0.4553504178,"remaining_time":0.5238977926},
{"learn":[3.997483319],"iteration":465,"passed_time":0.4558968225,"remaining_time":0.5224225391},
{"learn":[3.99708333],"iteration":466,"passed_time":0.4564335688,"remaining_time":0.5209402402},
{"learn":[3.995860263],"iteration":467,"passed_time":0.4570579273,"remaining_time":0.5195615755},
{"learn":[3.994131111],"iteration":468,"passed_time":0.4576565217,"remaining_time":0.5181569574},
{"learn":[3.993125499],"iteration":469,"passed_time":0.4582650202,"remaining_time":0.5167669376},
{"learn":[3.992954084],"iteration":470,"passed_time":0.4590677966,"remaining_time":0.5155984382},
{"learn":[3.990635743],"iteration":471,"passed_time":0.4597024426,"remaining_time":0.5142434104},
{"learn":[3.986678254],"iteration":472,"passed_time":0.4603883797,"remaining_time":0.5129485752},
{"learn":[3.986393291],"iteration":473,"passed_time":0.4609201166,"remaining_time":0.5114851927},
{"learn":[3.986152671],"iteration":474,"passed_time":0.4614620595,"remaining_time":0.5100370132},
{"learn":[3.985596662],"iteration":475,"passed_time":0.46199511,"remaining_time":0.5085828522},
{"learn":[3.983853457],"iteration":476,"passed_time":0.4625482681,"remaining_time":0.5071546},
{"learn":[3.983263928],"iteration":477,"passed_time":0.4642948166,"remaining_time":0.5070332516},
{"learn":[3.980067202],"iteration":478,"passed_time":0.4650985935,"remaining_time":0.505879681},
{"learn":[3.978115407],"iteration":479,"passed_time":0.4657259278,"remaining_time":0.5045364217},
{"learn":[3.972661644],"iteration":480,"passed_time":0.4663097411,"remaining_time":0.5031491801},
{"learn":[3.969938254],"iteration":481,"passed_time":0.4668869519,"remaining_time":0.5017581766},
{"learn":[3.968211434],"iteration":482,"passed_time":0.4674546376,"remaining_time":0.500360347},
{"learn":[3.966113368],"iteration":483,"passed_time":0.4680051169,"remaining_time":0.4989476039},
{"learn":[3.962246044],"iteration":484,"passed_time":0.4685771914,"remaining_time":0.4975613476},
{"learn":[3.961319703],"iteration":485,"passed_time":0.4691580447,"remaining_time":0.4961877263},
{"learn":[3.96078191],"iteration":486,"passed_time":0.4697786364,"remaining_time":0.4948592206},
{"learn":[3.958913633],"iteration":487,"passed_time":0.4703818492,"remaining_time":0.4935153828},
{"learn":[3.957428286],"iteration":488,"passed_time":0.4709486518,"remaining_time":0.4921365257},
{"learn":[3.952641965],"iteration":489,"passed_time":0.4715108736,"remaining_time":0.4907562154},
{"learn":[3.951486786],"iteration":490,"passed_time":0.4720684335,"remaining_time":0.4893744045},
{"learn":[3.94938344],"iteration":491,"passed_time":0.4726336798,"remaining_time":0.4880038807},
{"learn":[3.947297924],"iteration":492,"passed_time":0.4731968743,"remaining_time":0.4866345137},
{"learn":[3.946284886],"iteration":493,"passed_time":0.4737592958,"remaining_time":0.4852676188},
{"learn":[3.943288204],"iteration":494,"passed_time":0.4743483964,"remaining_time":0.4839311923},
{"learn":[3.943076488],"iteration":495,"passed_time":0.4749014701,"remaining_time":0.4825611712},
{"learn":[3.942347078],"iteration":496,"passed_time":0.475477391,"remaining_time":0.4812175607},
{"learn":[3.940251541],"iteration":497,"passed_time":0.4760966319,"remaining_time":0.4799207012},
{"learn":[3.939011019],"iteration":498,"passed_time":0.4766685691,"remaining_time":0.4785790644},
{"learn":[3.938760512],"iteration":499,"passed_time":0.4772041056,"remaining_time":0.4772041056},
{"learn":[3.934522727],"iteration":500,"passed_time":0.4777659577,"remaining_time":0.4758587083},
{"learn":[3.930091193],"iteration":501,"passed_time":0.4786712933,"remaining_time":0.4748571794},
{"learn":[3.927671752],"iteration":502,"passed_time":0.479388099,"remaining_time":0.4736697519},
{"learn":[3.927280041],"iteration":503,"passed_time":0.479990282,"remaining_time":0.4723713886},
{"learn":[3.925987561],"iteration":504,"passed_time":0.4805467587,"remaining_time":0.4710309813},
{"learn":[3.921645957],"iteration":505,"passed_time":0.4812002496,"remaining_time":0.469788386},
{"learn":[3.920333743],"iteration":506,"passed_time":0.4819189702,"remaining_time":0.468611543},
{"learn":[3.918659461],"iteration":507,"passed_time":0.4824929998,"remaining_time":0.4672963699},
{"learn":[3.916124385],"iteration":508,"passed_time":0.4830580538,"remaining_time":0.4659754507},
{"learn":[3.913849268],"iteration":509,"passed_time":0.4835995236,"remaining_time":0.4646348364},
{"learn":[3.912826119],"iteration":510,"passed_time":0.4841392133,"remaining_time":0.4632956464},
{"learn":[3.910034145],"iteration":511,"passed_time":0.4846591523,"remaining_time":0.4619407546},
{"learn":[3.90792379],"iteration":512,"passed_time":0.4852452139,"remaining_time":0.4606518892},
{"learn":[3.907823851],"iteration":513,"passed_time":0.4857400426,"remaining_time":0.4592794956},
{"learn":[3.904527401],"iteration":514,"passed_time":0.4862647267,"remaining_time":0.4579386261},
{"learn":[3.903378283],"iteration":515,"passed_time":0.4867857539,"remaining_time":0.4565974901},
{"learn":[3.902170135],"iteration":516,"passed_time":0.4873081579,"remaining_time":0.4552608129},
{"learn":[3.899435429],"iteration":517,"passed_time":0.4879538557,"remaining_time":0.4540420048},
{"learn":[3.897497505],"iteration":518,"passed_time":0.488606563,"remaining_time":0.4528319013},
{"learn":[3.896426119],"iteration":519,"passed_time":0.4892124418,"remaining_time":0.4515807155},
{"learn":[3.896044669],"iteration":520,"passed_time":0.4897699458,"remaining_time":0.4502875318},
{"learn":[3.892795942],"iteration":521,"passed_time":0.4903499699,"remaining_time":0.4490177885},
{"learn":[3.892413888],"iteration":522,"passed_time":0.4909065479,"remaining_time":0.4477292989},
{"learn":[3.891738985],"iteration":523,"passed_time":0.4914484069,"remaining_time":0.4464302322},
{"learn":[3.88822057],"iteration":524,"passed_time":0.4920400981,"remaining_time":0.4451791364},
{"learn":[3.883837053],"iteration":525,"passed_time":0.4926091188,"remaining_time":0.4439101184},
{"learn":[3.881769742],"iteration":526,"passed_time":0.493436855,"remaining_time":0.4428759628},
{"learn":[3.880356898],"iteration":527,"passed_time":0.4942227766,"remaining_time":0.4418052094},
{"learn":[3.879250273],"iteration":528,"passed_time":0.4949633299,"remaining_time":0.4406951387},
{"learn":[3.877174493],"iteration":529,"passed_time":0.4956591114,"remaining_time":0.4395467592},
{"learn":[3.875854201],"iteration":530,"passed_time":0.496297557,"remaining_time":0.438349443},
{"learn":[3.873189396],"iteration":531,"passed_time":0.4969130153,"remaining_time":0.4371340059},
{"learn":[3.871583368],"iteration":532,"passed_time":0.497551944,"remaining_time":0.4359413843},
{"learn":[3.869622679],"iteration":533,"passed_time":0.4981405404,"remaining_time":0.4347069135},
{"learn":[3.866860164],"iteration":534,"passed_time":0.4986891681,"remaining_time":0.433440118},
{"learn":[3.864498444],"iteration":535,"passed_time":0.4992315324,"remaining_time":0.4321705803},
{"learn":[3.861416322],"iteration":536,"passed_time":0.4997896391,"remaining_time":0.4309173238},
{"learn":[3.860265769],"iteration":537,"passed_time":0.500380717,"remaining_time":0.4296949651},
{"learn":[3.859328725],"iteration":538,"passed_time":0.5010341091,"remaining_time":0.4285282454},
{"learn":[3.858521278],"iteration":539,"passed_time":0.5016047857,"remaining_time":0.4272929656},
{"learn":[3.85599111],"iteration":540,"passed_time":0.5022959906,"remaining_time":0.4261624023},
{"learn":[3.852379816],"iteration":541,"passed_time":0.5028912494,"remaining_time":0.4249523842},
{"learn":[3.851327537],"iteration":542,"passed_time":0.5034735957,"remaining_time":0.4237337629},
{"learn":[3.847854898],"iteration":543,"passed_time":0.504019696,"remaining_time":0.4224870981},
{"learn":[3.847083414],"iteration":544,"passed_time":0.5045362883,"remaining_time":0.4212183692},
{"learn":[3.845397429],"iteration":545,"passed_time":0.5050599236,"remaining_time":0.4199582515},
{"learn":[3.841933528],"iteration":546,"passed_time":0.5055977683,"remaining_time":0.4187125942},
{"learn":[3.840996474],"iteration":547,"passed_time":0.5061943217,"remaining_time":0.4175179441},
{"learn":[3.838355966],"iteration":548,"passed_time":0.5069324599,"remaining_time":0.416441784},
{"learn":[3.83342799],"iteration":549,"passed_time":0.5075683947,"remaining_time":0.415283232},
{"learn":[3.828161535],"iteration":550,"passed_time":0.5088905941,"remaining_time":0.4146858017},
{"learn":[3.823502399],"iteration":551,"passed_time":0.5095737328,"remaining_time":0.4135670875},
{"learn":[3.820068862],"iteration":552,"passed_time":0.5102009471,"remaining_time":0.4124047439},
{"learn":[3.817951642],"iteration":553,"passed_time":0.5108356159,"remaining_time":0.4112503334},
{"learn":[3.815785958],"iteration":554,"passed_time":0.5114506544,"remaining_time":0.4100820562},
{"learn":[3.81503012],"iteration":555,"passed_time":0.5120275029,"remaining_time":0.4088852721},
{"learn":[3.813529315],"iteration":556,"passed_time":0.5126580565,"remaining_time":0.4077334274},
{"learn":[3.808881326],"iteration":557,"passed_time":0.5133025202,"remaining_time":0.4065944694},
{"learn":[3.808740434],"iteration":558,"passed_time":0.5138742449,"remaining_time":0.4053998963},
{"learn":[3.80714352],"iteration":559,"passed_time":0.5144262454,"remaining_time":0.4041920499},
{"learn":[3.80573346],"iteration":560,"passed_time":0.514996585,"remaining_time":0.4030008927},
{"learn":[3.803370052],"iteration":561,"passed_time":0.5155529657,"remaining_time":0.4018010658},
{"learn":[3.803215211],"iteration":562,"passed_time":0.5163026781,"remaining_time":0.4007535885},
{"learn":[3.801309667],"iteration":563,"passed_time":0.5170596444,"remaining_time":0.3997127747},
{"learn":[3.800003847],"iteration":564,"passed_time":0.5178747208,"remaining_time":0.3987177054},
{"learn":[3.798026138],"iteration":565,"passed_time":0.5186138178,"remaining_time":0.3976650122},
{"learn":[3.794745847],"iteration":566,"passed_time":0.5193532944,"remaining_time":0.3966137151},
{"learn":[3.794312041],"iteration":567,"passed_time":0.5200478882,"remaining_time":0.3955293797},
{"learn":[3.792205926],"iteration":568,"passed_time":0.5206437297,"remaining_time":0.3943716125},
{"learn":[3.788991061],"iteration":569,"passed_time":0.5212354383,"remaining_time":0.3932126991},
{"learn":[3.787391572],"iteration":570,"passed_time":0.5218196743,"remaining_time":0.3920501581},
{"learn":[3.7826445],"iteration":571,"passed_time":0.5224132929,"remaining_time":0.3908966597},
{"learn":[3.781700331],"iteration":572,"passed_time":0.5234557137,"remaining_time":0.3900795633},
{"learn":[3.780045374],"iteration":573,"passed_time":0.5240667147,"remaining_time":0.3889414991},
{"learn":[3.775462644],"iteration":574,"passed_time":0.5247079579,"remaining_time":0.387827621},
{"learn":[3.773711943],"iteration":575,"passed_time":0.5253363608,"remaining_time":0.3867059323},
{"learn":[3.772415806],"iteration":576,"passed_time":0.5259462188,"remaining_time":0.3855723579},
{"learn":[3.770170875],"iteration":577,"passed_time":0.526534531,"remaining_time":0.3844248652},
{"learn":[3.765166479],"iteration":578,"passed_time":0.5271030219,"remaining_time":0.3832648916},
{"learn":[3.763976102],"iteration":579,"passed_time":0.5277039423,"remaining_time":0.3821304409},
{"learn":[3.760761708],"iteration":580,"passed_time":0.5282735146,"remaining_time":0.3809752197},
{"learn":[3.758155662],"iteration":581,"passed_time":0.5288409786,"remaining_time":0.3798204966},
{"learn":[3.756844548],"iteration":582,"passed_time":0.5297011298,"remaining_time":0.3788771374},
{"learn":[3.753098923],"iteration":583,"passed_time":0.5303851255,"remaining_time":0.3778085825},
{"learn":[3.751618946],"iteration":584,"passed_time":0.5311104522,"remaining_time":0.3767706627},
{"learn":[3.751398464],"iteration":585,"passed_time":0.5316870352,"remaining_time":0.3756287245},
{"learn":[3.749920103],"iteration":586,"passed_time":0.5322774014,"remaining_time":0.3744984102},
{"learn":[3.748237465],"iteration":587,"passed_time":0.5329182061,"remaining_time":0.3734052736},
{"learn":[3.746021536],"iteration":588,"passed_time":0.5335018953,"remaining_time":0.3722738183},
{"learn":[3.74417648],"iteration":589,"passed_time":0.5340510172,"remaining_time":0.3711201984},
{"learn":[3.738788389],"iteration":590,"passed_time":0.5346232295,"remaining_time":0.3699846038},
{"learn":[3.736021611],"iteration":591,"passed_time":0.5351797831,"remaining_time":0.3688401208},
{"learn":[3.734546151],"iteration":592,"passed_time":0.5357871219,"remaining_time":0.3677324766},
{"learn":[3.733527479],"iteration":593,"passed_time":0.5363871332,"remaining_time":0.3666215085},
{"learn":[3.733026392],"iteration":594,"passed_time":0.5375498096,"remaining_time":0.3658952486},
{"learn":[3.730314752],"iteration":595,"passed_time":0.5384740059,"remaining_time":0.3650058698},
{"learn":[3.727342596],"iteration":596,"passed_time":0.5390932009,"remaining_time":0.3639104857},
{"learn":[3.725459604],"iteration":597,"passed_time":0.5396765531,"remaining_time":0.3627925992},
{"learn":[3.723158842],"iteration":598,"passed_time":0.5402388584,"remaining_time":0.3616624077},
{"learn":[3.722362756],"iteration":599,"passed_time":0.5408675666,"remaining_time":0.3605783777},
{"learn":[3.721443615],"iteration":600,"passed_time":0.5415623932,"remaining_time":0.3595397585},
{"learn":[3.720743486],"iteration":601,"passed_time":0.5421432626,"remaining_time":0.3584269411},
{"learn":[3.720215334],"iteration":602,"passed_time":0.5429076415,"remaining_time":0.3574367059},
{"learn":[3.719436563],"iteration":603,"passed_time":0.5435673735,"remaining_time":0.3563786091},
{"learn":[3.715046574],"iteration":604,"passed_time":0.5441978187,"remaining_time":0.3553027081},
{"learn":[3.71443396],"iteration":605,"passed_time":0.5448119717,"remaining_time":0.3542176846},
{"learn":[3.712938941],"iteration":606,"passed_time":0.5453808456,"remaining_time":0.3531048967},
{"learn":[3.712814764],"iteration":607,"passed_time":0.5459121797,"remaining_time":0.3519696948},
{"learn":[3.71235348],"iteration":608,"passed_time":0.5464667915,"remaining_time":0.3508514211},
{"learn":[3.711223749],"iteration":609,"passed_time":0.5470047843,"remaining_time":0.3497243703},
{"learn":[3.710755648],"iteration":610,"passed_time":0.547550945,"remaining_time":0.3486044478},
{"learn":[3.708668039],"iteration":611,"passed_time":0.5481123702,"remaining_time":0.3474960778},
{"learn":[3.705623591],"iteration":612,"passed_time":0.5486838446,"remaining_time":0.3463958367},
{"learn":[3.704045802],"iteration":613,"passed_time":0.5492717334,"remaining_time":0.345307637},
{"learn":[3.699915209],"iteration":614,"passed_time":0.5498737435,"remaining_time":0.3442299045},
{"learn":[3.696182221],"iteration":615,"passed_time":0.550470641,"remaining_time":0.3431505294},
{"learn":[3.694263278],"iteration":616,"passed_time":0.5510198266,"remaining_time":0.3420431014},
{"learn":[3.693810229],"iteration":617,"passed_time":0.5515595693,"remaining_time":0.3409316431},
{"learn":[3.690900932],"iteration":618,"passed_time":0.5533154705,"remaining_time":0.3405705885},
{"learn":[3.688020895],"iteration":619,"passed_time":0.5539538132,"remaining_time":0.339520079},
{"learn":[3.685491894],"iteration":620,"passed_time":0.5545670323,"remaining_time":0.338455564},
{"learn":[3.684328128],"iteration":621,"passed_time":0.5551687691,"remaining_time":0.337385522},
{"learn":[3.680640153],"iteration":622,"passed_time":0.5558323651,"remaining_time":0.3363544168},
{"learn":[3.678932783],"iteration":623,"passed_time":0.5564637302,"remaining_time":0.3353050682},
{"learn":[3.674167041],"iteration":624,"passed_time":0.5570355198,"remaining_time":0.3342213119},
{"learn":[3.672200976],"iteration":625,"passed_time":0.557607828,"remaining_time":0.3331395011},
{"learn":[3.670606604],"iteration":626,"passed_time":0.558150472,"remaining_time":0.3320416684},
{"learn":[3.665506042],"iteration":627,"passed_time":0.5587053134,"remaining_time":0.3309528289},
{"learn":[3.664214007],"iteration":628,"passed_time":0.559264329,"remaining_time":0.3298681496},
{"learn":[3.66261643],"iteration":629,"passed_time":0.5598166902,"remaining_time":0.3287812307},
{"learn":[3.662118449],"iteration":630,"passed_time":0.560355415,"remaining_time":0.3276880319},
{"learn":[3.660871366],"iteration":631,"passed_time":0.561078108,"remaining_time":0.3267037085},
{"learn":[3.656695243],"iteration":632,"passed_time":0.5617182737,"remaining_time":0.3256723641},
{"learn":[3.654497801],"iteration":633,"passed_time":0.562312461,"remaining_time":0.3246157109},
{"learn":[3.654189134],"iteration":634,"passed_time":0.562889106,"remaining_time":0.323550431},
{"learn":[3.653957699],"iteration":635,"passed_time":0.5634312988,"remaining_time":0.3224669697},
{"learn":[3.651920725],"iteration":636,"passed_time":0.5639878483,"remaining_time":0.3213933892},
{"learn":[3.65106705],"iteration":637,"passed_time":0.5645209103,"remaining_time":0.3203081027},
{"learn":[3.650612844],"iteration":638,"passed_time":0.5650627317,"remaining_time":0.3192294932},
{"learn":[3.649884732],"iteration":639,"passed_time":0.5656169766,"remaining_time":0.3181595494},
{"learn":[3.646276182],"iteration":640,"passed_time":0.5661809619,"remaining_time":0.3170966698},
{"learn":[3.645808194],"iteration":641,"passed_time":0.5667189502,"remaining_time":0.3160208476},
{"learn":[3.645042989],"iteration":642,"passed_time":0.5675004643,"remaining_time":0.3150819063},
{"learn":[3.639864499],"iteration":643,"passed_time":0.5683744962,"remaining_time":0.3141945973},
{"learn":[3.637318478],"iteration":644,"passed_time":0.569051999,"remaining_time":0.3131991622},
{"learn":[3.636344905],"iteration":645,"passed_time":0.5696313733,"remaining_time":0.3121509383},
{"learn":[3.634754643],"iteration":646,"passed_time":0.570180128,"remaining_time":0.3110874578},
{"learn":[3.630724975],"iteration":647,"passed_time":0.5707152336,"remaining_time":0.3100181516},
{"learn":[3.629408252],"iteration":648,"passed_time":0.571237432,"remaining_time":0.308943511},
{"learn":[3.62790646],"iteration":649,"passed_time":0.5717724747,"remaining_time":0.3078774864},
{"learn":[3.627388973],"iteration":650,"passed_time":0.572308814,"remaining_time":0.3068137882},
{"learn":[3.625163557],"iteration":651,"passed_time":0.5728361657,"remaining_time":0.3057469105},
{"learn":[3.623701985],"iteration":652,"passed_time":0.5734951445,"remaining_time":0.3047516312},
{"learn":[3.622342639],"iteration":653,"passed_time":0.5741532701,"remaining_time":0.3037569288},
{"learn":[3.621130639],"iteration":654,"passed_time":0.5747723551,"remaining_time":0.3027426909},
{"learn":[3.619125665],"iteration":655,"passed_time":0.5753699159,"remaining_time":0.3017183705},
{"learn":[3.618878783],"iteration":656,"passed_time":0.57591405,"remaining_time":0.3006674569},
{"learn":[3.616207429],"iteration":657,"passed_time":0.5764727203,"remaining_time":0.2996256388},
{"learn":[3.61206486],"iteration":658,"passed_time":0.5770321819,"remaining_time":0.2985856965},
{"learn":[3.611955873],"iteration":659,"passed_time":0.5775674764,"remaining_time":0.2975347606},
{"learn":[3.610713743],"iteration":660,"passed_time":0.5781322719,"remaining_time":0.2965005147},
{"learn":[3.610044025],"iteration":661,"passed_time":0.5786841657,"remaining_time":0.2954610997},
{"learn":[3.607342669],"iteration":662,"passed_time":0.5792357795,"remaining_time":0.2944230131},
{"learn":[3.602510618],"iteration":663,"passed_time":0.5801213607,"remaining_time":0.2935553873},
{"learn":[3.600492392],"iteration":664,"passed_time":0.5806813169,"remaining_time":0.2925236709},
{"learn":[3.597171065],"iteration":665,"passed_time":0.5812939739,"remaining_time":0.2915198007},
{"learn":[3.594358798],"iteration":666,"passed_time":0.5833394953,"remaining_time":0.2912324617},
{"learn":[3.593945251],"iteration":667,"passed_time":0.5839460669,"remaining_time":0.2902246919},
{"learn":[3.593607748],"iteration":668,"passed_time":0.5846099338,"remaining_time":0.2892464695},
{"learn":[3.592238714],"iteration":669,"passed_time":0.5852449761,"remaining_time":0.2882549882},
{"learn":[3.590144654],"iteration":670,"passed_time":0.585816489,"remaining_time":0.2872334201},
{"learn":[3.587151536],"iteration":671,"passed_time":0.5865926472,"remaining_time":0.2863130778},
{"learn":[3.586070865],"iteration":672,"passed_time":0.5873026354,"remaining_time":0.285361013},
{"learn":[3.585102746],"iteration":673,"passed_time":0.5879496815,"remaining_time":0.2843792228},
{"learn":[3.584362847],"iteration":674,"passed_time":0.5885656579,"remaining_time":0.2833834649},
{"learn":[3.581407561],"iteration":675,"passed_time":0.5891554612,"remaining_time":0.2823762861},
{"learn":[3.57919422],"iteration":676,"passed_time":0.5897303555,"remaining_time":0.2813632272},
{"learn":[3.577632204],"iteration":677,"passed_time":0.5902969381,"remaining_time":0.2803475134},
{"learn":[3.573911195],"iteration":678,"passed_time":0.5908501661,"remaining_time":0.279326809},
{"learn":[3.573408216],"iteration":679,"passed_time":0.5913900887,"remaining_time":0.2783012182},
{"learn":[3.571076482],"iteration":680,"passed_time":0.5922330088,"remaining_time":0.2774189865},
{"learn":[3.568177107],"iteration":681,"passed_time":0.5928054093,"remaining_time":0.2764107334},
{"learn":[3.564824621],"iteration":682,"passed_time":0.5934236278,"remaining_time":0.275425022},
{"learn":[3.562475026],"iteration":683,"passed_time":0.5940442492,"remaining_time":0.2744414952},
{"learn":[3.561226889],"iteration":684,"passed_time":0.594617055,"remaining_time":0.2734370399},
{"learn":[3.559383467],"iteration":685,"passed_time":0.5951963375,"remaining_time":0.2724368075},
{"learn":[3.555209766],"iteration":686,"passed_time":0.5957554379,"remaining_time":0.2714286056},
{"learn":[3.55345383],"iteration":687,"passed_time":0.5963044287,"remaining_time":0.2704171247},
{"learn":[3.552300968],"iteration":688,"passed_time":0.5980648691,"remaining_time":0.2699538088},
{"learn":[3.551253986],"iteration":689,"passed_time":0.5988748448,"remaining_time":0.2690597129},
{"learn":[3.549807725],"iteration":690,"passed_time":0.5995334212,"remaining_time":0.2680981579},
{"learn":[3.547992926],"iteration":691,"passed_time":0.600110352,"remaining_time":0.2671011393},
{"learn":[3.545438607],"iteration":692,"passed_time":0.6006626383,"remaining_time":0.2660944155},
{"learn":[3.543313763],"iteration":693,"passed_time":0.6012084412,"remaining_time":0.2650861427},
{"learn":[3.542962896],"iteration":694,"passed_time":0.6017457003,"remaining_time":0.2640754512},
{"learn":[3.539800465],"iteration":695,"passed_time":0.6022746162,"remaining_time":0.263062476},
{"learn":[3.53953187],"iteration":696,"passed_time":0.6027928711,"remaining_time":0.2620462553},
{"learn":[3.536332425],"iteration":697,"passed_time":0.6033230203,"remaining_time":0.2610366076},
{"learn":[3.534993327],"iteration":698,"passed_time":0.6038476713,"remaining_time":0.2600259643},
{"learn":[3.531637011],"iteration":699,"passed_time":0.6045665676,"remaining_time":0.2590999576},
{"learn":[3.531040284],"iteration":700,"passed_time":0.6050891371,"remaining_time":0.2580908017},
{"learn":[3.529973872],"iteration":701,"passed_time":0.605647608,"remaining_time":0.2570982724},
{"learn":[3.527325183],"iteration":702,"passed_time":0.6062398651,"remaining_time":0.2561212517},
{"learn":[3.527200815],"iteration":703,"passed_time":0.606783799,"remaining_time":0.2551250064},
{"learn":[3.523459911],"iteration":704,"passed_time":0.6073557148,"remaining_time":0.254141753},
{"learn":[3.522729934],"iteration":705,"passed_time":0.6079175056,"remaining_time":0.2531554485},
{"learn":[3.522260582],"iteration":706,"passed_time":0.6084751845,"remaining_time":0.2521686408},
{"learn":[3.518641591],"iteration":707,"passed_time":0.6090609247,"remaining_time":0.2511946187},
{"learn":[3.516856405],"iteration":708,"passed_time":0.6096158889,"remaining_time":0.2502090602},
{"learn":[3.515083413],"iteration":709,"passed_time":0.6101629396,"remaining_time":0.2492214824},
{"learn":[3.514671214],"iteration":710,"passed_time":0.6107109118,"remaining_time":0.2482355183},
{"learn":[3.512617621],"iteration":711,"passed_time":0.6113784563,"remaining_time":0.2472991509},
{"learn":[3.510747971],"iteration":712,"passed_time":0.6123401328,"remaining_time":0.2464819328},
{"learn":[3.508149266],"iteration":713,"passed_time":0.6130596722,"remaining_time":0.2455673197},
{"learn":[3.504557165],"iteration":714,"passed_time":0.6136255757,"remaining_time":0.2445920127},
{"learn":[3.501367208],"iteration":715,"passed_time":0.6141703637,"remaining_time":0.2436094739},
{"learn":[3.497593362],"iteration":716,"passed_time":0.6147428167,"remaining_time":0.2426390755},
{"learn":[3.496291169],"iteration":717,"passed_time":0.6153516374,"remaining_time":0.2416840693},
{"learn":[3.49330374],"iteration":718,"passed_time":0.6158697488,"remaining_time":0.240694575},
{"learn":[3.490044385],"iteration":719,"passed_time":0.6165259545,"remaining_time":0.2397600934},
{"learn":[3.488891789],"iteration":720,"passed_time":0.6171021401,"remaining_time":0.238795419},
{"learn":[3.486869081],"iteration":721,"passed_time":0.6176509754,"remaining_time":0.2378212897},
{"learn":[3.486303638],"iteration":722,"passed_time":0.6182527056,"remaining_time":0.2368686023},
{"learn":[3.486035862],"iteration":723,"passed_time":0.6188441698,"remaining_time":0.2359129708},
{"learn":[3.482668951],"iteration":724,"passed_time":0.619422659,"remaining_time":0.2349534224},
{"learn":[3.47820549],"iteration":725,"passed_time":0.6199797925,"remaining_time":0.2339868638},
{"learn":[3.474392283],"iteration":726,"passed_time":0.6205393024,"remaining_time":0.233022324},
{"learn":[3.472268163],"iteration":727,"passed_time":0.6210986667,"remaining_time":0.2320588425},
{"learn":[3.471209164],"iteration":728,"passed_time":0.6216580765,"remaining_time":0.2310964866},
{"learn":[3.470049971],"iteration":729,"passed_time":0.6222366162,"remaining_time":0.2301423101},
{"learn":[3.469078654],"iteration":730,"passed_time":0.6227975306,"remaining_time":0.2291826754},
{"learn":[3.468643292],"iteration":731,"passed_time":0.6233841646,"remaining_time":0.2282335466},
{"learn":[3.468134848],"iteration":732,"passed_time":0.6239296271,"remaining_time":0.2272704099},
{"learn":[3.467820182],"iteration":733,"passed_time":0.6245642525,"remaining_time":0.2263407236},
{"learn":[3.465776156],"iteration":734,"passed_time":0.6253079927,"remaining_time":0.2254511811},
{"learn":[3.463037608],"iteration":735,"passed_time":0.6258939331,"remaining_time":0.2245054325},
{"learn":[3.45965637],"iteration":736,"passed_time":0.6264843067,"remaining_time":0.2235622424},
{"learn":[3.457275091],"iteration":737,"passed_time":0.6272426498,"remaining_time":0.2226796399},
{"learn":[3.455522955],"iteration":738,"passed_time":0.6279664723,"remaining_time":0.2217851817},
{"learn":[3.451270508],"iteration":739,"passed_time":0.628545,"remaining_time":0.2208401351},
{"learn":[3.450978947],"iteration":740,"passed_time":0.6290764412,"remaining_time":0.2198796198},
{"learn":[3.450608492],"iteration":741,"passed_time":0.6300007901,"remaining_time":0.2190568785},
{"learn":[3.448122004],"iteration":742,"passed_time":0.6306627604,"remaining_time":0.2181431082},
{"learn":[3.445646714],"iteration":743,"passed_time":0.6313945481,"remaining_time":0.2172540381},
{"learn":[3.44411263],"iteration":744,"passed_time":0.6320218113,"remaining_time":0.2163296133},
{"learn":[3.443264164],"iteration":745,"passed_time":0.6326045369,"remaining_time":0.2153908209},
{"learn":[3.439521363],"iteration":746,"passed_time":0.6331761726,"remaining_time":0.2144492258},
{"learn":[3.436809225],"iteration":747,"passed_time":0.6337452719,"remaining_time":0.2135077654},
{"learn":[3.435509465],"iteration":748,"passed_time":0.6343040998,"remaining_time":0.2125638572},
{"learn":[3.434450277],"iteration":749,"passed_time":0.6348770821,"remaining_time":0.211625694},
{"learn":[3.431786753],"iteration":750,"passed_time":0.6354748353,"remaining_time":0.2106967164},
{"learn":[3.430150302],"iteration":751,"passed_time":0.6361726161,"remaining_time":0.2098016074},
{"learn":[3.42696281],"iteration":752,"passed_time":0.6367263433,"remaining_time":0.20885977},
{"learn":[3.426870334],"iteration":753,"passed_time":0.6372166197,"remaining_time":0.2078982605},
{"learn":[3.425200309],"iteration":754,"passed_time":0.6377567731,"remaining_time":0.2069541846},
{"learn":[3.423383783],"iteration":755,"passed_time":0.6382814402,"remaining_time":0.2060061791},
{"learn":[3.422752979],"iteration":756,"passed_time":0.6387815239,"remaining_time":0.2050514007},
{"learn":[3.420845924],"iteration":757,"passed_time":0.639357384,"remaining_time":0.2041220144},
{"learn":[3.418917862],"iteration":758,"passed_time":0.6400259952,"remaining_time":0.2032230103},
{"learn":[3.417095735],"iteration":759,"passed_time":0.6406317045,"remaining_time":0.2023047488},
{"learn":[3.414391848],"iteration":760,"passed_time":0.6412229825,"remaining_time":0.2013827764},
{"learn":[3.41426711],"iteration":761,"passed_time":0.6418379073,"remaining_time":0.2004690576},
{"learn":[3.411976013],"iteration":762,"passed_time":0.6425724676,"remaining_time":0.1995932829},
{"learn":[3.408614844],"iteration":763,"passed_time":0.6433209807,"remaining_time":0.1987221877},
{"learn":[3.407906721],"iteration":764,"passed_time":0.6440492777,"remaining_time":0.197845203},
{"learn":[3.407494015],"iteration":765,"passed_time":0.6447355961,"remaining_time":0.1969557826},
{"learn":[3.406287128],"iteration":766,"passed_time":0.6453519109,"remaining_time":0.1960456261},
{"learn":[3.404600442],"iteration":767,"passed_time":0.6459247336,"remaining_time":0.1951230966},
{"learn":[3.404012662],"iteration":768,"passed_time":0.6464686038,"remaining_time":0.1941927796},
{"learn":[3.400398762],"iteration":769,"passed_time":0.6470161752,"remaining_time":0.1932645718},
{"learn":[3.399737714],"iteration":770,"passed_time":0.6478571258,"remaining_time":0.19242449},
{"learn":[3.399185251],"iteration":771,"passed_time":0.6485876782,"remaining_time":0.1915518013},
{"learn":[3.397245411],"iteration":772,"passed_time":0.649231854,"remaining_time":0.190654115},
{"learn":[3.396229831],"iteration":773,"passed_time":0.6498034554,"remaining_time":0.1897358927},
{"learn":[3.394002836],"iteration":774,"passed_time":0.6503818136,"remaining_time":0.1888205265},
{"learn":[3.389617243],"iteration":775,"passed_time":0.6509351028,"remaining_time":0.1878987926},
{"learn":[3.385426488],"iteration":776,"passed_time":0.6514962405,"remaining_time":0.1869802595},
{"learn":[3.385072258],"iteration":777,"passed_time":0.6520460718,"remaining_time":0.1860594189},
{"learn":[3.383842366],"iteration":778,"passed_time":0.6526052814,"remaining_time":0.1851421915},
{"learn":[3.380110746],"iteration":779,"passed_time":0.6533151773,"remaining_time":0.1842683833},
{"learn":[3.378595218],"iteration":780,"passed_time":0.6538997409,"remaining_time":0.1833598505},
{"learn":[3.377371219],"iteration":781,"passed_time":0.6545142073,"remaining_time":0.1824604823},
{"learn":[3.375814782],"iteration":782,"passed_time":0.6552304753,"remaining_time":0.1815900551},
{"learn":[3.374195887],"iteration":783,"passed_time":0.6559332373,"remaining_time":0.1807163001},
{"learn":[3.373704309],"iteration":784,"passed_time":0.6581605109,"remaining_time":0.1802605221},
{"learn":[3.372971757],"iteration":785,"passed_time":0.6591974121,"remaining_time":0.1794761402},
{"learn":[3.371565136],"iteration":786,"passed_time":0.6616100646,"remaining_time":0.1790634609},
{"learn":[3.3700309],"iteration":787,"passed_time":0.6622857761,"remaining_time":0.1781784068},
{"learn":[3.368186663],"iteration":788,"passed_time":0.6628804353,"remaining_time":0.1772722077},
{"learn":[3.366710398],"iteration":789,"passed_time":0.6634453462,"remaining_time":0.1763588895},
{"learn":[3.364598042],"iteration":790,"passed_time":0.6640103067,"remaining_time":0.1754464654},
{"learn":[3.36348442],"iteration":791,"passed_time":0.6645726707,"remaining_time":0.1745342368},
{"learn":[3.362001759],"iteration":792,"passed_time":0.6651302281,"remaining_time":0.1736216358},
{"learn":[3.361580401],"iteration":793,"passed_time":0.6656771018,"remaining_time":0.1727071574},
{"learn":[3.359543675],"iteration":794,"passed_time":0.666235612,"remaining_time":0.1717966044},
{"learn":[3.35766119],"iteration":795,"passed_time":0.6668037882,"remaining_time":0.170889413},
{"learn":[3.354592969],"iteration":796,"passed_time":0.6677676918,"remaining_time":0.1700838663},
{"learn":[3.350985986],"iteration":797,"passed_time":0.6684222072,"remaining_time":0.1691996063},
{"learn":[3.349589624],"iteration":798,"passed_time":0.6690879113,"remaining_time":0.1683187361},
{"learn":[3.349110856],"iteration":799,"passed_time":0.6697388079,"remaining_time":0.167434702},
{"learn":[3.345315441],"iteration":800,"passed_time":0.6703775161,"remaining_time":0.1665482219},
{"learn":[3.34397474],"iteration":801,"passed_time":0.6710594435,"remaining_time":0.1656730297},
{"learn":[3.343800902],"iteration":802,"passed_time":0.6730312287,"remaining_time":0.1651147597},
{"learn":[3.342329465],"iteration":803,"passed_time":0.674269935,"remaining_time":0.1643742628},
{"learn":[3.34220347],"iteration":804,"passed_time":0.6751353227,"remaining_time":0.1635420968},
{"learn":[3.341279219],"iteration":805,"passed_time":0.6757696817,"remaining_time":0.162654241},
{"learn":[3.337329521],"iteration":806,"passed_time":0.6763545893,"remaining_time":0.1617551868},
{"learn":[3.336708453],"iteration":807,"passed_time":0.6769825998,"remaining_time":0.1608671524},
{"learn":[3.333252703],"iteration":808,"passed_time":0.6775733775,"remaining_time":0.1599709705},
{"learn":[3.332186769],"iteration":809,"passed_time":0.6781514887,"remaining_time":0.1590725714},
{"learn":[3.330594851],"iteration":810,"passed_time":0.6788321637,"remaining_time":0.1581988643},
{"learn":[3.327867442],"iteration":811,"passed_time":0.6794693983,"remaining_time":0.157315575},
{"learn":[3.327563111],"iteration":812,"passed_time":0.6802504087,"remaining_time":0.1564659612},
{"learn":[3.326308994],"iteration":813,"passed_time":0.6809300332,"remaining_time":0.1555933491},
{"learn":[3.326249879],"iteration":814,"passed_time":0.6816027579,"remaining_time":0.1547196444},
{"learn":[3.322336238],"iteration":815,"passed_time":0.682202679,"remaining_time":0.1538300159},
{"learn":[3.320491154],"iteration":816,"passed_time":0.6827727581,"remaining_time":0.1529344121},
{"learn":[3.320434271],"iteration":817,"passed_time":0.6833088703,"remaining_time":0.1520320469},
{"learn":[3.319609638],"iteration":818,"passed_time":0.6838667999,"remaining_time":0.1511353978},
{"learn":[3.316182682],"iteration":819,"passed_time":0.6844417617,"remaining_time":0.1502433135},
{"learn":[3.313126612],"iteration":820,"passed_time":0.6850248037,"remaining_time":0.1493537635},
{"learn":[3.311222803],"iteration":821,"passed_time":0.6857028739,"remaining_time":0.1484855372},
{"learn":[3.309627335],"iteration":822,"passed_time":0.687009975,"remaining_time":0.1477530566},
{"learn":[3.307974895],"iteration":823,"passed_time":0.6876894386,"remaining_time":0.1468851228},
{"learn":[3.307321505],"iteration":824,"passed_time":0.6882992688,"remaining_time":0.1460028752},
{"learn":[3.306759087],"iteration":825,"passed_time":0.6888951355,"remaining_time":0.1451183457},
{"learn":[3.30484037],"iteration":826,"passed_time":0.689694875,"remaining_time":0.1442771625},
{"learn":[3.30201994],"iteration":827,"passed_time":0.6903305583,"remaining_time":0.143402},
{"learn":[3.299302297],"iteration":828,"passed_time":0.6909307674,"remaining_time":0.142520098},
{"learn":[3.298132671],"iteration":829,"passed_time":0.6915671711,"remaining_time":0.1416462881},
{"learn":[3.296976183],"iteration":830,"passed_time":0.6921474615,"remaining_time":0.1407616378},
{"learn":[3.293144745],"iteration":831,"passed_time":0.6927173271,"remaining_time":0.1398756141},
{"learn":[3.290284404],"iteration":832,"passed_time":0.6932771212,"remaining_time":0.1389883304},
{"learn":[3.288285745],"iteration":833,"passed_time":0.6938344163,"remaining_time":0.1381013347},
{"learn":[3.286662667],"iteration":834,"passed_time":0.6944098707,"remaining_time":0.137218717},
{"learn":[3.285692682],"iteration":835,"passed_time":0.6949625403,"remaining_time":0.1363323644},
{"learn":[3.284565611],"iteration":836,"passed_time":0.6957088655,"remaining_time":0.1354845222},
{"learn":[3.283897383],"iteration":837,"passed_time":0.6964063188,"remaining_time":0.1346274745},
{"learn":[3.280712855],"iteration":838,"passed_time":0.6971718801,"remaining_time":0.1337838769},
{"learn":[3.280468341],"iteration":839,"passed_time":0.6977564313,"remaining_time":0.1329059869},
{"learn":[3.277814895],"iteration":840,"passed_time":0.6983512174,"remaining_time":0.1320307296},
{"learn":[3.276316385],"iteration":841,"passed_time":0.699000235,"remaining_time":0.1311663149},
{"learn":[3.27557063],"iteration":842,"passed_time":0.6996137288,"remaining_time":0.1302957953},
{"learn":[3.27499628],"iteration":843,"passed_time":0.7002763355,"remaining_time":0.1294349625},
{"learn":[3.273569958],"iteration":844,"passed_time":0.7018455543,"remaining_time":0.1287409005},
{"learn":[3.269665595],"iteration":845,"passed_time":0.7027223373,"remaining_time":0.1279187233},
{"learn":[3.267984685],"iteration":846,"passed_time":0.7034688883,"remaining_time":0.1270728925},
{"learn":[3.267702508],"iteration":847,"passed_time":0.7042335572,"remaining_time":0.1262305433},
{"learn":[3.266671924],"iteration":848,"passed_time":0.7049693993,"remaining_time":0.12538325},
{"learn":[3.265359825],"iteration":849,"passed_time":0.7056244135,"remaining_time":0.1245219553},
{"learn":[3.2618983],"iteration":850,"passed_time":0.7062320281,"remaining_time":0.1236528463},
{"learn":[3.260456253],"iteration":851,"passed_time":0.7068172315,"remaining_time":0.122780458},
{"learn":[3.258389147],"iteration":852,"passed_time":0.707433157,"remaining_time":0.1219140376},
{"learn":[3.258108469],"iteration":853,"passed_time":0.7079875112,"remaining_time":0.1210376776},
{"learn":[3.256424936],"iteration":854,"passed_time":0.7086741679,"remaining_time":0.120184508},
{"learn":[3.254817983],"iteration":855,"passed_time":0.7095359102,"remaining_time":0.1193611811},
{"learn":[3.253898449],"iteration":856,"passed_time":0.7102551928,"remaining_time":0.1185139937},
{"learn":[3.253023652],"iteration":857,"passed_time":0.7110535674,"remaining_time":0.1176801941},
{"learn":[3.252845542],"iteration":858,"passed_time":0.7118063797,"remaining_time":0.1168389983},
{"learn":[3.252316026],"iteration":859,"passed_time":0.7124783392,"remaining_time":0.1159848459},
{"learn":[3.24975301],"iteration":860,"passed_time":0.713178372,"remaining_time":0.1151356489},
{"learn":[3.249151075],"iteration":861,"passed_time":0.7138426873,"remaining_time":0.1142810799},
{"learn":[3.246257135],"iteration":862,"passed_time":0.7144514922,"remaining_time":0.1134181395},
{"learn":[3.243826471],"iteration":863,"passed_time":0.7151279983,"remaining_time":0.1125664442},
{"learn":[3.243190653],"iteration":864,"passed_time":0.7162195929,"remaining_time":0.1117799365},
{"learn":[3.24008797],"iteration":865,"passed_time":0.7171199685,"remaining_time":0.110963136},
{"learn":[3.240036811],"iteration":866,"passed_time":0.7180497709,"remaining_time":0.1101506569},
{"learn":[3.238676314],"iteration":867,"passed_time":0.7187747039,"remaining_time":0.1093067522},
{"learn":[3.237848782],"iteration":868,"passed_time":0.7194057526,"remaining_time":0.1084489685},
{"learn":[3.236405498],"iteration":869,"passed_time":0.720018874,"remaining_time":0.1075890272},
{"learn":[3.233378068],"iteration":870,"passed_time":0.7206092993,"remaining_time":0.1067262912},
{"learn":[3.233169169],"iteration":871,"passed_time":0.7211697754,"remaining_time":0.1058597835},
{"learn":[3.232434885],"iteration":872,"passed_time":0.7217879326,"remaining_time":0.1050023682},
{"learn":[3.229978115],"iteration":873,"passed_time":0.7223547092,"remaining_time":0.1041380931},
{"learn":[3.229648848],"iteration":874,"passed_time":0.7231586937,"remaining_time":0.1033083848},
{"learn":[3.227208761],"iteration":875,"passed_time":0.7237738108,"remaining_time":0.1024520006},
{"learn":[3.226258869],"iteration":876,"passed_time":0.724342771,"remaining_time":0.1015896931},
{"learn":[3.225331995],"iteration":877,"passed_time":0.7249207139,"remaining_time":0.1007293019},
{"learn":[3.221968268],"iteration":878,"passed_time":0.7254842666,"remaining_time":0.09986757254},
{"learn":[3.221166317],"iteration":879,"passed_time":0.7260387502,"remaining_time":0.09900528412},
{"learn":[3.220047503],"iteration":880,"passed_time":0.7266360811,"remaining_time":0.09814948201},
{"learn":[3.21982781],"iteration":881,"passed_time":0.7271907384,"remaining_time":0.09728855684},
{"learn":[3.216693405],"iteration":882,"passed_time":0.7278724801,"remaining_time":0.0964451644},
{"learn":[3.214798761],"iteration":883,"passed_time":0.7284759258,"remaining_time":0.09559186356},
{"learn":[3.214395085],"iteration":884,"passed_time":0.7291924035,"remaining_time":0.09475381514},
{"learn":[3.213470696],"iteration":885,"passed_time":0.7297749094,"remaining_time":0.09389880324},
{"learn":[3.211595017],"iteration":886,"passed_time":0.7303432576,"remaining_time":0.09304260215},
{"learn":[3.210965255],"iteration":887,"passed_time":0.7311819323,"remaining_time":0.09222114461},
{"learn":[3.209413583],"iteration":888,"passed_time":0.7318033101,"remaining_time":0.09137251679},
{"learn":[3.208331683],"iteration":889,"passed_time":0.7323963695,"remaining_time":0.0905208996},
{"learn":[3.207110711],"iteration":890,"passed_time":0.7329839634,"remaining_time":0.08966919417},
{"learn":[3.204519413],"iteration":891,"passed_time":0.7336080076,"remaining_time":0.0888224942},
{"learn":[3.201421296],"iteration":892,"passed_time":0.7343092911,"remaining_time":0.08798554776},
{"learn":[3.200691259],"iteration":893,"passed_time":0.7350613237,"remaining_time":0.08715492205},
{"learn":[3.200485067],"iteration":894,"passed_time":0.735732904,"remaining_time":0.08631503343},
{"learn":[3.197467568],"iteration":895,"passed_time":0.7363261466,"remaining_time":0.08546642773},
{"learn":[3.195838544],"iteration":896,"passed_time":0.7371184337,"remaining_time":0.08464124713},
{"learn":[3.195671746],"iteration":897,"passed_time":0.7377980673,"remaining_time":0.08380334395},
{"learn":[3.194213094],"iteration":898,"passed_time":0.7384219643,"remaining_time":0.08295953103},
{"learn":[3.192884691],"iteration":899,"passed_time":0.7390338318,"remaining_time":0.0821148702},
{"learn":[3.188364239],"iteration":900,"passed_time":0.7397471212,"remaining_time":0.08128187014},
{"learn":[3.185219478],"iteration":901,"passed_time":0.7404643293,"remaining_time":0.08044956127},
{"learn":[3.184120387],"iteration":902,"passed_time":0.7411988495,"remaining_time":0.079619367},
{"learn":[3.183725321],"iteration":903,"passed_time":0.7418920971,"remaining_time":0.07878500146},
{"learn":[3.181264554],"iteration":904,"passed_time":0.7425764389,"remaining_time":0.07795001292},
{"learn":[3.180741589],"iteration":905,"passed_time":0.7432475758,"remaining_time":0.07711398689},
{"learn":[3.179782639],"iteration":906,"passed_time":0.7438352743,"remaining_time":0.07626976903},
{"learn":[3.176377564],"iteration":907,"passed_time":0.7444297895,"remaining_time":0.07542680687},
{"learn":[3.174078182],"iteration":908,"passed_time":0.7450036669,"remaining_time":0.07458232529},
{"learn":[3.171242379],"iteration":909,"passed_time":0.7459200146,"remaining_time":0.07377230914},
{"learn":[3.170421012],"iteration":910,"passed_time":0.7467720609,"remaining_time":0.07295577762},
{"learn":[3.170087224],"iteration":911,"passed_time":0.7475604223,"remaining_time":0.0721330232},
{"learn":[3.167303059],"iteration":912,"passed_time":0.7482652964,"remaining_time":0.0713023886},
{"learn":[3.16705966],"iteration":913,"passed_time":0.74889027,"remaining_time":0.07046451118},
{"learn":[3.165667683],"iteration":914,"passed_time":0.7494742773,"remaining_time":0.06962329352},
{"learn":[3.164689733],"iteration":915,"passed_time":0.7500371525,"remaining_time":0.06878069957},
{"learn":[3.163311455],"iteration":916,"passed_time":0.7507299744,"remaining_time":0.06795047751},
{"learn":[3.159425016],"iteration":917,"passed_time":0.7513594784,"remaining_time":0.06711489894},
{"learn":[3.159327058],"iteration":918,"passed_time":0.7519198883,"remaining_time":0.06627367894},
{"learn":[3.15819426],"iteration":919,"passed_time":0.7525790656,"remaining_time":0.06544165788},
{"learn":[3.157086603],"iteration":920,"passed_time":0.7534205758,"remaining_time":0.06462565199},
{"learn":[3.153354154],"iteration":921,"passed_time":0.7541328072,"remaining_time":0.06379865397},
{"learn":[3.153261317],"iteration":922,"passed_time":0.7547197923,"remaining_time":0.06296145613},
{"learn":[3.153168454],"iteration":923,"passed_time":0.755293089,"remaining_time":0.06212367399},
{"learn":[3.152080399],"iteration":924,"passed_time":0.7558480987,"remaining_time":0.06128498097},
{"learn":[3.151635144],"iteration":925,"passed_time":0.7564123565,"remaining_time":0.06044763972},
{"learn":[3.147762655],"iteration":926,"passed_time":0.7569813656,"remaining_time":0.0596112618},
{"learn":[3.147172317],"iteration":927,"passed_time":0.7575416175,"remaining_time":0.05877478067},
{"learn":[3.146254125],"iteration":928,"passed_time":0.7581039857,"remaining_time":0.05793905595},
{"learn":[3.144869828],"iteration":929,"passed_time":0.7586551734,"remaining_time":0.05710307757},
{"learn":[3.143466218],"iteration":930,"passed_time":0.7592037966,"remaining_time":0.05626752091},
{"learn":[3.141919643],"iteration":931,"passed_time":0.7597889089,"remaining_time":0.05543524228},
{"learn":[3.141054135],"iteration":932,"passed_time":0.7616570427,"remaining_time":0.054695629},
{"learn":[3.139390417],"iteration":933,"passed_time":0.7622746503,"remaining_time":0.05386523225},
{"learn":[3.139025283],"iteration":934,"passed_time":0.7629900961,"remaining_time":0.05304209224},
{"learn":[3.137824183],"iteration":935,"passed_time":0.7636745715,"remaining_time":0.05221706472},
{"learn":[3.135620453],"iteration":936,"passed_time":0.7643044878,"remaining_time":0.05138866887},
{"learn":[3.13443178],"iteration":937,"passed_time":0.7649468844,"remaining_time":0.05056152115},
{"learn":[3.132765713],"iteration":938,"passed_time":0.7655733022,"remaining_time":0.0497337289},
{"learn":[3.131434124],"iteration":939,"passed_time":0.7662491495,"remaining_time":0.04890952018},
{"learn":[3.128384262],"iteration":940,"passed_time":0.7668622097,"remaining_time":0.04808169009},
{"learn":[3.128120455],"iteration":941,"passed_time":0.7674201997,"remaining_time":0.04725092525},
{"learn":[3.126314615],"iteration":942,"passed_time":0.7679973316,"remaining_time":0.04642189597},
{"learn":[3.125409666],"iteration":943,"passed_time":0.7685579846,"remaining_time":0.04559242282},
{"learn":[3.123072589],"iteration":944,"passed_time":0.7691201948,"remaining_time":0.04476360922},
{"learn":[3.122921099],"iteration":945,"passed_time":0.7696617006,"remaining_time":0.04393417741},
{"learn":[3.122182662],"iteration":946,"passed_time":0.7702254659,"remaining_time":0.04310659946},
{"learn":[3.120040951],"iteration":947,"passed_time":0.7708033641,"remaining_time":0.04228035331},
{"learn":[3.118767799],"iteration":948,"passed_time":0.771380264,"remaining_time":0.04145457688},
{"learn":[3.118203218],"iteration":949,"passed_time":0.7720357509,"remaining_time":0.04063346057},
{"learn":[3.116343362],"iteration":950,"passed_time":0.7726437791,"remaining_time":0.03981024729},
{"learn":[3.11480829],"iteration":951,"passed_time":0.7732330294,"remaining_time":0.0389865393},
{"learn":[3.112607903],"iteration":952,"passed_time":0.7738027395,"remaining_time":0.03816235966},
{"learn":[3.111661241],"iteration":953,"passed_time":0.7743720083,"remaining_time":0.03733869222},
{"learn":[3.110249676],"iteration":954,"passed_time":0.7749519029,"remaining_time":0.03651605825},
{"learn":[3.107333579],"iteration":955,"passed_time":0.7760549174,"remaining_time":0.03571800875},
{"learn":[3.107149851],"iteration":956,"passed_time":0.776656373,"remaining_time":0.03489678583},
{"learn":[3.106867336],"iteration":957,"passed_time":0.7772216503,"remaining_time":0.03407443561},
{"learn":[3.10364681],"iteration":958,"passed_time":0.7777840966,"remaining_time":0.03325250048},
{"learn":[3.102703811],"iteration":959,"passed_time":0.7785866324,"remaining_time":0.03244110968},
{"learn":[3.101469264],"iteration":960,"passed_time":0.779200782,"remaining_time":0.03162209209},
{"learn":[3.09863569],"iteration":961,"passed_time":0.7798327588,"remaining_time":0.03080420461},
{"learn":[3.09645939],"iteration":962,"passed_time":0.7804097823,"remaining_time":0.02998459184},
{"learn":[3.096240186],"iteration":963,"passed_time":0.7809531517,"remaining_time":0.02916422558},
{"learn":[3.094838828],"iteration":964,"passed_time":0.7815040797,"remaining_time":0.02834470756},
{"learn":[3.094176802],"iteration":965,"passed_time":0.7820635942,"remaining_time":0.02752604783},
{"learn":[3.093182279],"iteration":966,"passed_time":0.7826014869,"remaining_time":0.02670718621},
{"learn":[3.090150687],"iteration":967,"passed_time":0.7831608901,"remaining_time":0.0258896162},
{"learn":[3.088612829],"iteration":968,"passed_time":0.7837221044,"remaining_time":0.02507263698},
{"learn":[3.087153684],"iteration":969,"passed_time":0.7844000063,"remaining_time":0.02425979401},
{"learn":[3.085866843],"iteration":970,"passed_time":0.7850279763,"remaining_time":0.02344573771},
{"learn":[3.082669094],"iteration":971,"passed_time":0.7856542129,"remaining_time":0.02263201436},
{"learn":[3.081047548],"iteration":972,"passed_time":0.786231023,"remaining_time":0.02181730485},
{"learn":[3.079684322],"iteration":973,"passed_time":0.7868075118,"remaining_time":0.02100307526},
{"learn":[3.07613431],"iteration":974,"passed_time":0.787363945,"remaining_time":0.0201888191},
{"learn":[3.074005935],"iteration":975,"passed_time":0.7879306947,"remaining_time":0.01937534495},
{"learn":[3.072988853],"iteration":976,"passed_time":0.7884851382,"remaining_time":0.01856208616},
{"learn":[3.072344268],"iteration":977,"passed_time":0.7890458533,"remaining_time":0.01774949772},
{"learn":[3.070654438],"iteration":978,"passed_time":0.7896059091,"remaining_time":0.01693740969},
{"learn":[3.069724506],"iteration":979,"passed_time":0.7911854397,"remaining_time":0.01614664163},
{"learn":[3.067763166],"iteration":980,"passed_time":0.7919144295,"remaining_time":0.01533779221},
{"learn":[3.066737893],"iteration":981,"passed_time":0.7928266092,"remaining_time":0.0145324633},
{"learn":[3.065248174],"iteration":982,"passed_time":0.7935553839,"remaining_time":0.0137237452},
{"learn":[3.063186837],"iteration":983,"passed_time":0.7941095077,"remaining_time":0.01291234972},
{"learn":[3.062880371],"iteration":984,"passed_time":0.7946449702,"remaining_time":0.01210119244},
{"learn":[3.061288645],"iteration":985,"passed_time":0.7951812996,"remaining_time":0.01129060669},
{"learn":[3.059970575],"iteration":986,"passed_time":0.7957312661,"remaining_time":0.01048075629},
{"learn":[3.059576341],"iteration":987,"passed_time":0.7962442366,"remaining_time":0.009670982631},
{"learn":[3.058175919],"iteration":988,"passed_time":0.7968732091,"remaining_time":0.008863099394},
{"learn":[3.056830702],"iteration":989,"passed_time":0.7975157352,"remaining_time":0.008055714497},
{"learn":[3.056336579],"iteration":990,"passed_time":0.7981044499,"remaining_time":0.007248173611},
{"learn":[3.055810414],"iteration":991,"passed_time":0.7986648808,"remaining_time":0.006440845813},
{"learn":[3.055476518],"iteration":992,"passed_time":0.7992030796,"remaining_time":0.005633858567},
{"learn":[3.053331734],"iteration":993,"passed_time":0.7997689392,"remaining_time":0.00482757911},
{"learn":[3.050890374],"iteration":994,"passed_time":0.8003312801,"remaining_time":0.004021765227},
{"learn":[3.04972623],"iteration":995,"passed_time":0.8008900956,"remaining_time":0.003216426087},
{"learn":[3.047217327],"iteration":996,"passed_time":0.8014559528,"remaining_time":0.002411602666},
{"learn":[3.047155483],"iteration":997,"passed_time":0.802003597,"remaining_time":0.001607221637},
{"learn":[3.04430671],"iteration":998,"passed_time":0.8025574172,"remaining_time":0.000803360778},
{"learn":[3.042664195],"iteration":999,"passed_time":0.8031453614,"remaining_time":0}
]}